{"British": [{"id": "th_52893", "name": "Apple & Blackberry Crumble", "thumb": "https://www.themealdb.com/images/media/meals/xvsurr1511719182.jpg", "category": "Dessert"}, {"id": "th_52768", "name": "Apple Frangipan Tart", "thumb": "https://www.themealdb.com/images/media/meals/wxywrq1468235067.jpg", "category": "Dessert"}, {"id": "th_52959", "name": "Baked salmon with fennel & tomatoes", "thumb": "https://www.themealdb.com/images/media/meals/1548772327.jpg", "category": "Seafood"}, {"id": "th_52767", "name": "Bakewell tart", "thumb": "https://www.themealdb.com/images/media/meals/wyrqqq1468233628.jpg", "category": "Dessert"}, {"id": "th_52894", "name": "Battenberg Cake", "thumb": "https://www.themealdb.com/images/media/meals/ywwrsp1511720277.jpg", "category": "Dessert"}, {"id": "th_52848", "name": "Bean & Sausage Hotpot", "thumb": "https://www.themealdb.com/images/media/meals/vxuyrx1511302687.jpg", "category": "Miscellaneous"}, {"id": "th_52873", "name": "Beef Dumpling Stew", "thumb": "https://www.themealdb.com/images/media/meals/uyqrrv1511553350.jpg", "category": "Beef"}, {"id": "th_52824", "name": "Beef Sunday Roast", "thumb": "https://www.themealdb.com/images/media/meals/ssrrrs1503664277.jpg", "category": "Beef"}, {"id": "th_52803", "name": "Beef Wellington", "thumb": "https://www.themealdb.com/images/media/meals/vvpprx1487325699.jpg", "category": "Beef"}, {"id": "th_52874", "name": "Beef and Mustard Pie", "thumb": "https://www.themealdb.com/images/media/meals/sytuqu1511553755.jpg", "category": "Beef"}, {"id": "th_52878", "name": "Beef and Oyster pie", "thumb": "https://www.themealdb.com/images/media/meals/wrssvt1511556563.jpg", "category": "Beef"}, {"id": "th_52891", "name": "Blackberry Fool", "thumb": "https://www.themealdb.com/images/media/meals/rpvptu1511641092.jpg", "category": "Dessert"}, {"id": "th_52792", "name": "Bread and Butter Pudding", "thumb": "https://www.themealdb.com/images/media/meals/xqwwpy1483908697.jpg", "category": "Dessert"}, {"id": "th_52842", "name": "Broccoli & Stilton soup", "thumb": "https://www.themealdb.com/images/media/meals/tvvxpv1511191952.jpg", "category": "Starter"}, {"id": "th_52897", "name": "Carrot Cake", "thumb": "https://www.themealdb.com/images/media/meals/vrspxv1511722107.jpg", "category": "Dessert"}, {"id": "th_52898", "name": "Chelsea Buns", "thumb": "https://www.themealdb.com/images/media/meals/vqpwrv1511723001.jpg", "category": "Dessert"}, {"id": "th_52846", "name": "Chicken & mushroom Hotpot", "thumb": "https://www.themealdb.com/images/media/meals/uuuspp1511297945.jpg", "category": "Chicken"}, {"id": "th_52875", "name": "Chicken Ham and Leek Pie", "thumb": "https://www.themealdb.com/images/media/meals/xrrtss1511555269.jpg", "category": "Chicken"}, {"id": "th_52853", "name": "Chocolate Avocado Mousse", "thumb": "https://www.themealdb.com/images/media/meals/uttuxy1511382180.jpg", "category": "Dessert"}, {"id": "th_52966", "name": "Chocolate Caramel Crispy", "thumb": "https://www.themealdb.com/images/media/meals/1550442508.jpg", "category": "Dessert"}, {"id": "th_52788", "name": "Christmas Pudding Flapjack", "thumb": "https://www.themealdb.com/images/media/meals/vvusxs1483907034.jpg", "category": "Dessert"}, {"id": "th_52989", "name": "Christmas Pudding Trifle", "thumb": "https://www.themealdb.com/images/media/meals/r33cud1576791081.jpg", "category": "Dessert"}, {"id": "th_52990", "name": "Christmas cake", "thumb": "https://www.themealdb.com/images/media/meals/ldnrm91576791881.jpg", "category": "Dessert"}, {"id": "th_52988", "name": "Classic Christmas pudding", "thumb": "https://www.themealdb.com/images/media/meals/1d85821576790598.jpg", "category": "Dessert"}, {"id": "th_53096", "name": "Corned Beef Hash", "thumb": "https://www.themealdb.com/images/media/meals/vz94r81760534692.jpg", "category": "Beef"}, {"id": "th_52841", "name": "Creamy Tomato Soup", "thumb": "https://www.themealdb.com/images/media/meals/stpuws1511191310.jpg", "category": "Starter"}, {"id": "th_53098", "name": "Cumberland Pie", "thumb": "https://www.themealdb.com/images/media/meals/pvfkz61761595976.jpg", "category": "Beef"}, {"id": "th_52899", "name": "Dundee cake", "thumb": "https://www.themealdb.com/images/media/meals/wxyvqq1511723401.jpg", "category": "Dessert"}, {"id": "th_52888", "name": "Eccles Cakes", "thumb": "https://www.themealdb.com/images/media/meals/wtqrqw1511639627.jpg", "category": "Dessert"}, {"id": "th_52895", "name": "English Breakfast", "thumb": "https://www.themealdb.com/images/media/meals/utxryw1511721587.jpg", "category": "Breakfast"}, {"id": "th_52791", "name": "Eton Mess", "thumb": "https://www.themealdb.com/images/media/meals/uuxwvq1483907861.jpg", "category": "Dessert"}, {"id": "th_52802", "name": "Fish pie", "thumb": "https://www.themealdb.com/images/media/meals/ysxwuq1487323065.jpg", "category": "Seafood"}, {"id": "th_52896", "name": "Full English Breakfast", "thumb": "https://www.themealdb.com/images/media/meals/sqrtwu1511721265.jpg", "category": "Breakfast"}, {"id": "th_52890", "name": "Jam Roly-Poly", "thumb": "https://www.themealdb.com/images/media/meals/ysqupp1511640538.jpg", "category": "Dessert"}, {"id": "th_52887", "name": "Kedgeree", "thumb": "https://www.themealdb.com/images/media/meals/utxqpt1511639216.jpg", "category": "Seafood"}, {"id": "th_52877", "name": "Lamb and Potato pie", "thumb": "https://www.themealdb.com/images/media/meals/sxrpws1511555907.jpg", "category": "Lamb"}, {"id": "th_52884", "name": "Lancashire hotpot", "thumb": "https://www.themealdb.com/images/media/meals/uttrxw1511637813.jpg", "category": "Lamb"}, {"id": "th_52900", "name": "Madeira Cake", "thumb": "https://www.themealdb.com/images/media/meals/urtqut1511723591.jpg", "category": "Dessert"}, {"id": "th_52880", "name": "McSinghs Scotch pie", "thumb": "https://www.themealdb.com/images/media/meals/vssrtx1511557680.jpg", "category": "Lamb"}, {"id": "th_52991", "name": "Mince Pies", "thumb": "https://www.themealdb.com/images/media/meals/qe8pf51576795532.jpg", "category": "Dessert"}, {"id": "th_52876", "name": "Minced Beef Pie", "thumb": "https://www.themealdb.com/images/media/meals/xwutvy1511555540.jpg", "category": "Beef"}, {"id": "th_52864", "name": "Mushroom & Chestnut Rotolo", "thumb": "https://www.themealdb.com/images/media/meals/ssyqwr1511451678.jpg", "category": "Vegetarian"}, {"id": "th_52902", "name": "Parkin Cake", "thumb": "https://www.themealdb.com/images/media/meals/qxuqtt1511724269.jpg", "category": "Dessert"}, {"id": "th_52901", "name": "Rock Cakes", "thumb": "https://www.themealdb.com/images/media/meals/tqrrsq1511723764.jpg", "category": "Dessert"}, {"id": "th_52960", "name": "Salmon Avocado Salad", "thumb": "https://www.themealdb.com/images/media/meals/1549542994.jpg", "category": "Seafood"}, {"id": "th_52784", "name": "Smoky Lentil Chili with Squash", "thumb": "https://www.themealdb.com/images/media/meals/uwxqwy1483389553.jpg", "category": "Vegetarian"}, {"id": "th_52886", "name": "Spotted Dick", "thumb": "https://www.themealdb.com/images/media/meals/xqvyqr1511638875.jpg", "category": "Dessert"}, {"id": "th_52881", "name": "Steak and Kidney Pie", "thumb": "https://www.themealdb.com/images/media/meals/qysyss1511558054.jpg", "category": "Beef"}, {"id": "th_52883", "name": "Sticky Toffee Pudding", "thumb": "https://www.themealdb.com/images/media/meals/xqqqtu1511637379.jpg", "category": "Dessert"}, {"id": "th_52793", "name": "Sticky Toffee Pudding Ultimate", "thumb": "https://www.themealdb.com/images/media/meals/xrptpq1483909204.jpg", "category": "Dessert"}, {"id": "th_53005", "name": "Strawberry Rhubarb Pie", "thumb": "https://www.themealdb.com/images/media/meals/178z5o1585514569.jpg", "category": "Dessert"}, {"id": "th_52889", "name": "Summer Pudding", "thumb": "https://www.themealdb.com/images/media/meals/rsqwus1511640214.jpg", "category": "Dessert"}, {"id": "th_52882", "name": "Three Fish Pie", "thumb": "https://www.themealdb.com/images/media/meals/spswqs1511558697.jpg", "category": "Seafood"}, {"id": "th_52822", "name": "Toad In The Hole", "thumb": "https://www.themealdb.com/images/media/meals/ytuvwr1503070420.jpg", "category": "Pork"}, {"id": "th_52892", "name": "Treacle Tart", "thumb": "https://www.themealdb.com/images/media/meals/wprvrw1511641295.jpg", "category": "Dessert"}, {"id": "th_52845", "name": "Turkey Meatloaf", "thumb": "https://www.themealdb.com/images/media/meals/ypuxtw1511297463.jpg", "category": "Miscellaneous"}, {"id": "th_52863", "name": "Vegetarian Casserole", "thumb": "https://www.themealdb.com/images/media/meals/vptwyt1511450962.jpg", "category": "Vegetarian"}, {"id": "th_52867", "name": "Vegetarian Chilli", "thumb": "https://www.themealdb.com/images/media/meals/wqurxy1511453156.jpg", "category": "Vegetarian"}, {"id": "th_53097", "name": "Yorkshire Puddings", "thumb": "https://www.themealdb.com/images/media/meals/x5qz5k1761595900.jpg", "category": "Miscellaneous"}], "Spanish": [{"id": "th_53158", "name": "Air fryer patatas bravas", "thumb": "https://www.themealdb.com/images/media/meals/3m8yae1763257951.jpg", "category": "Vegetarian"}, {"id": "th_53169", "name": "Ajo blanco", "thumb": "https://www.themealdb.com/images/media/meals/5jdtie1763289302.jpg", "category": "Starter"}, {"id": "th_53156", "name": "Arroz al horno (baked rice)", "thumb": "https://www.themealdb.com/images/media/meals/qt4i0n1763256454.jpg", "category": "Pork"}, {"id": "th_53147", "name": "Arroz con gambas y calamar", "thumb": "https://www.themealdb.com/images/media/meals/jc6oub1763196663.jpg", "category": "Seafood"}, {"id": "th_53161", "name": "Chicken & chorizo rice pot", "thumb": "https://www.themealdb.com/images/media/meals/fk80jp1763280767.jpg", "category": "Chicken"}, {"id": "th_53186", "name": "Chicken with saffron, raisins & pine nuts", "thumb": "https://www.themealdb.com/images/media/meals/4mhr3u1763481087.jpg", "category": "Chicken"}, {"id": "th_53166", "name": "Chickpea, chorizo & spinach stew", "thumb": "https://www.themealdb.com/images/media/meals/xvnx8j1763287209.jpg", "category": "Pork"}, {"id": "th_53170", "name": "Chocolate churros with chocolate & salted caramel sauce", "thumb": "https://www.themealdb.com/images/media/meals/erzs951763296201.jpg", "category": "Dessert"}, {"id": "th_53168", "name": "Chorizo & chickpea soup", "thumb": "https://www.themealdb.com/images/media/meals/kggfo91763288633.jpg", "category": "Pork"}, {"id": "th_53157", "name": "Chorizo & soft-boiled egg salad", "thumb": "https://www.themealdb.com/images/media/meals/v8eaed1763257313.jpg", "category": "Pork"}, {"id": "th_53185", "name": "Chorizo & tomato salad", "thumb": "https://www.themealdb.com/images/media/meals/6cskio1763338156.jpg", "category": "Pork"}, {"id": "th_53159", "name": "Chorizo, potato & cheese omelette", "thumb": "https://www.themealdb.com/images/media/meals/0y6uvc1763258983.jpg", "category": "Pork"}, {"id": "th_53153", "name": "Churros", "thumb": "https://www.themealdb.com/images/media/meals/nxnny61763250596.jpg", "category": "Dessert"}, {"id": "th_53154", "name": "Clam, chorizo & white bean stew", "thumb": "https://www.themealdb.com/images/media/meals/92wbmf1763252334.jpg", "category": "Seafood"}, {"id": "th_53148", "name": "Crema Catalana", "thumb": "https://www.themealdb.com/images/media/meals/x73ll91763247842.jpg", "category": "Dessert"}, {"id": "th_53143", "name": "Easy Spanish chicken", "thumb": "https://www.themealdb.com/images/media/meals/kzxflc1763194887.jpg", "category": "Chicken"}, {"id": "th_53149", "name": "Ensaimada", "thumb": "https://www.themealdb.com/images/media/meals/1ugsho1763248007.jpg", "category": "Dessert"}, {"id": "th_53178", "name": "Fried calamari", "thumb": "https://www.themealdb.com/images/media/meals/yhi46r1763330279.jpg", "category": "Seafood"}, {"id": "th_53144", "name": "Gambas al ajillo", "thumb": "https://www.themealdb.com/images/media/meals/ze8uwg1763196123.jpg", "category": "Seafood"}, {"id": "th_53180", "name": "Garlicky prawns with sherry", "thumb": "https://www.themealdb.com/images/media/meals/u2lhqb1763331899.jpg", "category": "Seafood"}, {"id": "th_53179", "name": "Ham croquetas", "thumb": "https://www.themealdb.com/images/media/meals/6dpa7m1763331105.jpg", "category": "Pork"}, {"id": "th_53145", "name": "Jamon & wild garlic croquetas", "thumb": "https://www.themealdb.com/images/media/meals/zc9cwz1763196177.jpg", "category": "Pork"}, {"id": "th_53086", "name": "Migas", "thumb": "https://www.themealdb.com/images/media/meals/xd9aj21740432378.jpg", "category": "Miscellaneous"}, {"id": "th_53150", "name": "Padron peppers", "thumb": "https://www.themealdb.com/images/media/meals/0ljvc51763248075.jpg", "category": "Vegan"}, {"id": "th_53151", "name": "Paella", "thumb": "https://www.themealdb.com/images/media/meals/9bl20p1763248192.jpg", "category": "Seafood"}, {"id": "th_53152", "name": "Pan-fried hake, white bean & chorizo broth", "thumb": "https://www.themealdb.com/images/media/meals/4yjart1763248459.jpg", "category": "Seafood"}, {"id": "th_53172", "name": "Patatas bravas", "thumb": "https://www.themealdb.com/images/media/meals/bvg8sn1763298713.jpg", "category": "Vegetarian"}, {"id": "th_53160", "name": "Pisto con huevos", "thumb": "https://www.themealdb.com/images/media/meals/0nswfe1763279040.jpg", "category": "Vegetarian"}, {"id": "th_53162", "name": "Pollo en pepitoria", "thumb": "https://www.themealdb.com/images/media/meals/li30ck1763281992.jpg", "category": "Chicken"}, {"id": "th_53174", "name": "Prawns with Romesco sauce", "thumb": "https://www.themealdb.com/images/media/meals/u03xhi1763308917.jpg", "category": "Seafood"}, {"id": "th_53173", "name": "Quick gazpacho", "thumb": "https://www.themealdb.com/images/media/meals/h5qmn31763304965.jpg", "category": "Starter"}, {"id": "th_52942", "name": "Roast fennel and aubergine paella", "thumb": "https://www.themealdb.com/images/media/meals/1520081754.jpg", "category": "Vegan"}, {"id": "th_53171", "name": "Salt cod tortilla", "thumb": "https://www.themealdb.com/images/media/meals/njj1681763297231.jpg", "category": "Seafood"}, {"id": "th_52836", "name": "Seafood fideuà", "thumb": "https://www.themealdb.com/images/media/meals/wqqvyq1511179730.jpg", "category": "Seafood"}, {"id": "th_53167", "name": "Seafood rice", "thumb": "https://www.themealdb.com/images/media/meals/5r5rvx1763287943.jpg", "category": "Seafood"}, {"id": "th_53177", "name": "Spaghetti with Spanish flavours", "thumb": "https://www.themealdb.com/images/media/meals/vpcqn01763335688.jpg", "category": "Pork"}, {"id": "th_53164", "name": "Spanish Chicken", "thumb": "https://www.themealdb.com/images/media/meals/pqulvm1763282839.jpg", "category": "Chicken"}, {"id": "th_52872", "name": "Spanish Tortilla", "thumb": "https://www.themealdb.com/images/media/meals/quuxsx1511476154.jpg", "category": "Vegetarian"}, {"id": "th_53181", "name": "Spanish beans with chicken & chorizo", "thumb": "https://www.themealdb.com/images/media/meals/bpkxtw1763332446.jpg", "category": "Chicken"}, {"id": "th_53155", "name": "Spanish chicken pie", "thumb": "https://www.themealdb.com/images/media/meals/8ovxf41763253962.jpg", "category": "Chicken"}, {"id": "th_53163", "name": "Spanish fig & almond balls", "thumb": "https://www.themealdb.com/images/media/meals/si2rty1763282314.jpg", "category": "Dessert"}, {"id": "th_53183", "name": "Spanish meatballs with clams, chorizo & squid", "thumb": "https://www.themealdb.com/images/media/meals/2wt8721763334199.jpg", "category": "Miscellaneous"}, {"id": "th_53184", "name": "Spanish rice & prawn one-pot", "thumb": "https://www.themealdb.com/images/media/meals/sl6vqv1763335988.jpg", "category": "Seafood"}, {"id": "th_53182", "name": "Spanish seafood rice", "thumb": "https://www.themealdb.com/images/media/meals/c6ghxm1763335584.jpg", "category": "Seafood"}, {"id": "th_53176", "name": "Spanish tomato bread with jamón Serrano", "thumb": "https://www.themealdb.com/images/media/meals/hsp1fo1763327867.jpg", "category": "Pork"}, {"id": "th_53175", "name": "Spanish-style slow-cooked lamb shoulder & beans", "thumb": "https://www.themealdb.com/images/media/meals/9kwatm1763327074.jpg", "category": "Lamb"}, {"id": "th_53142", "name": "Spiced tortilla", "thumb": "https://www.themealdb.com/images/media/meals/7b862e1763194846.jpg", "category": "Vegetarian"}, {"id": "th_53165", "name": "Torrijas with sherry", "thumb": "https://www.themealdb.com/images/media/meals/f3ee3y1763309332.jpg", "category": "Breakfast"}], "United States": [{"id": "th_52995", "name": "BBQ Pork Sloppy Joes", "thumb": "https://www.themealdb.com/images/media/meals/atd5sh1583188467.jpg", "category": "Pork"}, {"id": "th_52855", "name": "Banana Pancakes", "thumb": "https://www.themealdb.com/images/media/meals/sywswr1511383814.jpg", "category": "Dessert"}, {"id": "th_52812", "name": "Beef Brisket Pot Roast", "thumb": "https://www.themealdb.com/images/media/meals/ursuup1487348423.jpg", "category": "Beef"}, {"id": "th_53013", "name": "Big Mac", "thumb": "https://www.themealdb.com/images/media/meals/urzj1d1587670726.jpg", "category": "Beef"}, {"id": "th_53016", "name": "Chick-Fil-A Sandwich", "thumb": "https://www.themealdb.com/images/media/meals/sbx7n71587673021.jpg", "category": "Chicken"}, {"id": "th_52818", "name": "Chicken Fajita Mac and Cheese", "thumb": "https://www.themealdb.com/images/media/meals/qrqywr1503066605.jpg", "category": "Chicken"}, {"id": "th_52856", "name": "Choc Chip Pecan Pie", "thumb": "https://www.themealdb.com/images/media/meals/rqvwxt1511384809.jpg", "category": "Dessert"}, {"id": "th_52860", "name": "Chocolate Raspberry Brownies", "thumb": "https://www.themealdb.com/images/media/meals/yypvst1511386427.jpg", "category": "Dessert"}, {"id": "th_52840", "name": "Clam chowder", "thumb": "https://www.themealdb.com/images/media/meals/rvtvuw1511190488.jpg", "category": "Starter"}, {"id": "th_52779", "name": "Cream Cheese Tart", "thumb": "https://www.themealdb.com/images/media/meals/wurrux1468416624.jpg", "category": "Starter"}, {"id": "th_52996", "name": "French Onion Chicken with Roasted Carrots & Mashed Potatoes", "thumb": "https://www.themealdb.com/images/media/meals/b5ft861583188991.jpg", "category": "Chicken"}, {"id": "th_52957", "name": "Fruit and Cream Cheese Breakfast Pastries", "thumb": "https://www.themealdb.com/images/media/meals/1543774956.jpg", "category": "Breakfast"}, {"id": "th_52829", "name": "Grilled Mac and Cheese Sandwich", "thumb": "https://www.themealdb.com/images/media/meals/xutquv1505330523.jpg", "category": "Pasta"}, {"id": "th_52993", "name": "Honey Balsamic Chicken with Crispy Broccoli & Potatoes", "thumb": "https://www.themealdb.com/images/media/meals/kvbotn1581012881.jpg", "category": "Chicken"}, {"id": "th_52787", "name": "Hot Chocolate Fudge", "thumb": "https://www.themealdb.com/images/media/meals/xrysxr1483568462.jpg", "category": "Dessert"}, {"id": "th_52813", "name": "Kentucky Fried Chicken", "thumb": "https://www.themealdb.com/images/media/meals/40r49m1763197022.jpg", "category": "Chicken"}, {"id": "th_52859", "name": "Key Lime Pie", "thumb": "https://www.themealdb.com/images/media/meals/qpqtuu1511386216.jpg", "category": "Dessert"}, {"id": "th_53015", "name": "Krispy Kreme Donut", "thumb": "https://www.themealdb.com/images/media/meals/4i5cnx1587672171.jpg", "category": "Dessert"}, {"id": "th_52987", "name": "Lasagna Sandwiches", "thumb": "https://www.themealdb.com/images/media/meals/xr0n4r1576788363.jpg", "category": "Pasta"}, {"id": "th_52858", "name": "New York cheesecake", "thumb": "https://www.themealdb.com/images/media/meals/swttys1511385853.jpg", "category": "Dessert"}, {"id": "th_52854", "name": "Pancakes", "thumb": "https://www.themealdb.com/images/media/meals/rwuyqx1511383174.jpg", "category": "Dessert"}, {"id": "th_52862", "name": "Peach & Blueberry Grunt", "thumb": "https://www.themealdb.com/images/media/meals/ssxvup1511387476.jpg", "category": "Dessert"}, {"id": "th_52861", "name": "Peanut Butter Cheesecake", "thumb": "https://www.themealdb.com/images/media/meals/qtuuys1511387068.jpg", "category": "Dessert"}, {"id": "th_52958", "name": "Peanut Butter Cookies", "thumb": "https://www.themealdb.com/images/media/meals/1544384070.jpg", "category": "Dessert"}, {"id": "th_52857", "name": "Pumpkin Pie", "thumb": "https://www.themealdb.com/images/media/meals/usuqtp1511385394.jpg", "category": "Dessert"}, {"id": "th_52816", "name": "Roasted Eggplant With Tahini, Pine Nuts, and Lentils", "thumb": "https://www.themealdb.com/images/media/meals/ysqrus1487425681.jpg", "category": "Vegetarian"}, {"id": "th_52786", "name": "Rocky Road Fudge", "thumb": "https://www.themealdb.com/images/media/meals/vtxyxv1483567157.jpg", "category": "Dessert"}, {"id": "th_52962", "name": "Salmon Eggs Eggs Benedict", "thumb": "https://www.themealdb.com/images/media/meals/1550440197.jpg", "category": "Breakfast"}, {"id": "th_52833", "name": "Salted Caramel Cheescake", "thumb": "https://www.themealdb.com/images/media/meals/xqrwyr1511133646.jpg", "category": "Dessert"}, {"id": "th_52994", "name": "Skillet Apple Pork Chops with Roasted Sweet Potatoes & Zucchini", "thumb": "https://www.themealdb.com/images/media/meals/h3ijwo1581013377.jpg", "category": "Pork"}, {"id": "th_52992", "name": "Soy-Glazed Meatloaves with Wasabi Mashed Potatoes & Roasted Carrots", "thumb": "https://www.themealdb.com/images/media/meals/o2wb6p1581005243.jpg", "category": "Beef"}, {"id": "th_52817", "name": "Stovetop Eggplant With Harissa, Chickpeas, and Cumin Yogurt", "thumb": "https://www.themealdb.com/images/media/meals/yqwtvu1487426027.jpg", "category": "Vegetarian"}, {"id": "th_52794", "name": "Vegan Chocolate Cake", "thumb": "https://www.themealdb.com/images/media/meals/qxutws1486978099.jpg", "category": "Vegan"}], "Turkish": [{"id": "th_53262", "name": "Adana kebab", "thumb": "https://www.themealdb.com/images/media/meals/04axct1763793018.jpg", "category": "Lamb"}, {"id": "th_53276", "name": "Apricot & Turkish delight mess", "thumb": "https://www.themealdb.com/images/media/meals/p277uc1764109195.jpg", "category": "Dessert"}, {"id": "th_53278", "name": "Aubergine & hummus grills", "thumb": "https://www.themealdb.com/images/media/meals/zub3s91764110535.jpg", "category": "Vegetarian"}, {"id": "th_53267", "name": "Aubergine couscous salad", "thumb": "https://www.themealdb.com/images/media/meals/02s6gc1763799560.jpg", "category": "Vegetarian"}, {"id": "th_53279", "name": "Baklava with spiced nuts, ricotta & chocolate", "thumb": "https://www.themealdb.com/images/media/meals/ytme8t1764111401.jpg", "category": "Dessert"}, {"id": "th_53256", "name": "Cacik", "thumb": "https://www.themealdb.com/images/media/meals/16zbeu1763789342.jpg", "category": "Side"}, {"id": "th_53261", "name": "Chicken wings with cumin, lemon & garlic", "thumb": "https://www.themealdb.com/images/media/meals/4hzyvq1763792564.jpg", "category": "Chicken"}, {"id": "th_53265", "name": "Chilli ginger lamb chops", "thumb": "https://www.themealdb.com/images/media/meals/8xuvhj1763794991.jpg", "category": "Lamb"}, {"id": "th_52977", "name": "Corba", "thumb": "https://www.themealdb.com/images/media/meals/58oia61564916529.jpg", "category": "Side"}, {"id": "th_53254", "name": "Ezme", "thumb": "https://www.themealdb.com/images/media/meals/pb6mj11763788331.jpg", "category": "Vegetarian"}, {"id": "th_53266", "name": "Falafel", "thumb": "https://www.themealdb.com/images/media/meals/u5e9qq1763795441.jpg", "category": "Vegetarian"}, {"id": "th_53274", "name": "Griddled aubergines with sesame dressing", "thumb": "https://www.themealdb.com/images/media/meals/yoj48r1763817100.jpg", "category": "Vegetarian"}, {"id": "th_53272", "name": "Griddled flatbreads", "thumb": "https://www.themealdb.com/images/media/meals/8825lo1763815264.jpg", "category": "Side"}, {"id": "th_53255", "name": "Grilled aubergines with spicy chickpeas & walnut sauce", "thumb": "https://www.themealdb.com/images/media/meals/ctw3ba1763788978.jpg", "category": "Vegetarian"}, {"id": "th_53258", "name": "Hot cumin lamb wrap with crunchy slaw & spicy mayo", "thumb": "https://www.themealdb.com/images/media/meals/jyylmo1763790808.jpg", "category": "Lamb"}, {"id": "th_53269", "name": "Hummus", "thumb": "https://www.themealdb.com/images/media/meals/gpon5u1763801180.jpg", "category": "Side"}, {"id": "th_53253", "name": "Imam bayildi with BBQ lamb & tzatziki", "thumb": "https://www.themealdb.com/images/media/meals/ampz9v1763787134.jpg", "category": "Lamb"}, {"id": "th_52978", "name": "Kumpir", "thumb": "https://www.themealdb.com/images/media/meals/mlchx21564916997.jpg", "category": "Side"}, {"id": "th_53277", "name": "Lamb & apricot meatballs", "thumb": "https://www.themealdb.com/images/media/meals/72fgzj1764109947.jpg", "category": "Lamb"}, {"id": "th_53273", "name": "Roast aubergine with goat's cheese & toasted flatbread", "thumb": "https://www.themealdb.com/images/media/meals/iydbwy1763816111.jpg", "category": "Vegetarian"}, {"id": "th_53268", "name": "Roasted chicken with creamy walnut sauce", "thumb": "https://www.themealdb.com/images/media/meals/ro8mzj1763800655.jpg", "category": "Chicken"}, {"id": "th_53260", "name": "Slow-roast lamb with cinnamon, fennel & citrus", "thumb": "https://www.themealdb.com/images/media/meals/gr4lo51763791826.jpg", "category": "Lamb"}, {"id": "th_53259", "name": "Smoked aubergine purée", "thumb": "https://www.themealdb.com/images/media/meals/8c8m4q1763791156.jpg", "category": "Side"}, {"id": "th_53264", "name": "Smoky chicken skewers", "thumb": "https://www.themealdb.com/images/media/meals/3um6il1763794322.jpg", "category": "Chicken"}, {"id": "th_53275", "name": "Sweet potato salad", "thumb": "https://www.themealdb.com/images/media/meals/z458v91763817681.jpg", "category": "Vegetarian"}, {"id": "th_53263", "name": "Turkish lamb pilau", "thumb": "https://www.themealdb.com/images/media/meals/cr2kyr1763793839.jpg", "category": "Lamb"}, {"id": "th_53252", "name": "Turkish rice (vermicelli rice)", "thumb": "https://www.themealdb.com/images/media/meals/xw1ruy1763786501.jpg", "category": "Miscellaneous"}, {"id": "th_53270", "name": "Turkish-style lamb", "thumb": "https://www.themealdb.com/images/media/meals/0p7l6b1763813981.jpg", "category": "Lamb"}, {"id": "th_53271", "name": "Walnut, date & honey cake", "thumb": "https://www.themealdb.com/images/media/meals/towo9c1763814590.jpg", "category": "Dessert"}, {"id": "th_53257", "name": "kofta burgers", "thumb": "https://www.themealdb.com/images/media/meals/lgmnff1763789847.jpg", "category": "Lamb"}], "France": [{"id": "th_52904", "name": "Beef Bourguignon", "thumb": "https://www.themealdb.com/images/media/meals/vtqxtu1511784197.jpg", "category": "Beef"}, {"id": "th_52914", "name": "Boulangère Potatoes", "thumb": "https://www.themealdb.com/images/media/meals/qywups1511796761.jpg", "category": "Side"}, {"id": "th_52913", "name": "Brie wrapped in prosciutto & brioche", "thumb": "https://www.themealdb.com/images/media/meals/qqpwsy1511796276.jpg", "category": "Side"}, {"id": "th_52934", "name": "Chicken Basquaise", "thumb": "https://www.themealdb.com/images/media/meals/wruvqv1511880994.jpg", "category": "Chicken"}, {"id": "th_52920", "name": "Chicken Marengo", "thumb": "https://www.themealdb.com/images/media/meals/qpxvuq1511798906.jpg", "category": "Chicken"}, {"id": "th_52879", "name": "Chicken Parmentier", "thumb": "https://www.themealdb.com/images/media/meals/uwvxpv1511557015.jpg", "category": "Chicken"}, {"id": "th_52910", "name": "Chinon Apple Tarts", "thumb": "https://www.themealdb.com/images/media/meals/qtqwwu1511792650.jpg", "category": "Dessert"}, {"id": "th_52776", "name": "Chocolate Gateau", "thumb": "https://www.themealdb.com/images/media/meals/tqtywx1468317395.jpg", "category": "Dessert"}, {"id": "th_52905", "name": "Chocolate Souffle", "thumb": "https://www.themealdb.com/images/media/meals/twspvx1511784937.jpg", "category": "Dessert"}, {"id": "th_52832", "name": "Coq au vin", "thumb": "https://www.themealdb.com/images/media/meals/qstyvs1505931190.jpg", "category": "Chicken"}, {"id": "th_52907", "name": "Duck Confit", "thumb": "https://www.themealdb.com/images/media/meals/wvpvsu1511786158.jpg", "category": "Miscellaneous"}, {"id": "th_52919", "name": "Fennel Dauphinoise", "thumb": "https://www.themealdb.com/images/media/meals/ytttsv1511798734.jpg", "category": "Side"}, {"id": "th_52918", "name": "Fish Stew with Rouille", "thumb": "https://www.themealdb.com/images/media/meals/vptqpw1511798500.jpg", "category": "Seafood"}, {"id": "th_52906", "name": "Flamiche", "thumb": "https://www.themealdb.com/images/media/meals/wssvvs1511785879.jpg", "category": "Vegetarian"}, {"id": "th_52815", "name": "French Lentils With Garlic and Thyme", "thumb": "https://www.themealdb.com/images/media/meals/vwwspt1487394060.jpg", "category": "Miscellaneous"}, {"id": "th_52915", "name": "French Omelette", "thumb": "https://www.themealdb.com/images/media/meals/yvpuuy1511797244.jpg", "category": "Miscellaneous"}, {"id": "th_52903", "name": "French Onion Soup", "thumb": "https://www.themealdb.com/images/media/meals/xvrrux1511783685.jpg", "category": "Side"}, {"id": "th_52916", "name": "Pear Tarte Tatin", "thumb": "https://www.themealdb.com/images/media/meals/rxvxrr1511797671.jpg", "category": "Dessert"}, {"id": "th_52847", "name": "Pork Cassoulet", "thumb": "https://www.themealdb.com/images/media/meals/wxuvuv1511299147.jpg", "category": "Pork"}, {"id": "th_52922", "name": "Prawn & Fennel Bisque", "thumb": "https://www.themealdb.com/images/media/meals/rtwwvv1511799504.jpg", "category": "Side"}, {"id": "th_52921", "name": "Provençal Omelette Cake", "thumb": "https://www.themealdb.com/images/media/meals/qwtrtp1511799242.jpg", "category": "Vegetarian"}, {"id": "th_52908", "name": "Ratatouille", "thumb": "https://www.themealdb.com/images/media/meals/wrpwuu1511786491.jpg", "category": "Vegetarian"}, {"id": "th_52935", "name": "Steak Diane", "thumb": "https://www.themealdb.com/images/media/meals/vussxq1511882648.jpg", "category": "Beef"}, {"id": "th_52911", "name": "Summer Pistou", "thumb": "https://www.themealdb.com/images/media/meals/rqtxvr1511792990.jpg", "category": "Vegetarian"}, {"id": "th_52909", "name": "Tarte Tatin", "thumb": "https://www.themealdb.com/images/media/meals/ryspuw1511786688.jpg", "category": "Dessert"}, {"id": "th_52912", "name": "Three-cheese souffles", "thumb": "https://www.themealdb.com/images/media/meals/sxwquu1511793428.jpg", "category": "Miscellaneous"}, {"id": "th_52852", "name": "Tuna Nicoise", "thumb": "https://www.themealdb.com/images/media/meals/yypwwq1511304979.jpg", "category": "Seafood"}, {"id": "th_52917", "name": "White chocolate creme brulee", "thumb": "https://www.themealdb.com/images/media/meals/uryqru1511798039.jpg", "category": "Dessert"}], "Chinese": [{"id": "th_53373", "name": "Air Fryer Egg Rolls", "thumb": "https://www.themealdb.com/images/media/meals/grhn401765687086.jpg", "category": "Side"}, {"id": "th_52952", "name": "Beef Lo Mein", "thumb": "https://www.themealdb.com/images/media/meals/1529444830.jpg", "category": "Beef"}, {"id": "th_53366", "name": "Beef and Broccoli Stir-Fry", "thumb": "https://www.themealdb.com/images/media/meals/m0p0j81765568742.jpg", "category": "Beef"}, {"id": "th_52956", "name": "Chicken Congee", "thumb": "https://www.themealdb.com/images/media/meals/1529446352.jpg", "category": "Chicken"}, {"id": "th_53367", "name": "Chicken Fried Rice", "thumb": "https://www.themealdb.com/images/media/meals/wuyd2h1765655837.jpg", "category": "Chicken"}, {"id": "th_53365", "name": "Chinese Orange Chicken", "thumb": "https://www.themealdb.com/images/media/meals/s73ytv1765567838.jpg", "category": "Chicken"}, {"id": "th_53372", "name": "Chinese Tomato Egg Stir Fry", "thumb": "https://www.themealdb.com/images/media/meals/rwvw8q1765660071.jpg", "category": "Vegetarian"}, {"id": "th_52955", "name": "Egg Drop Soup", "thumb": "https://www.themealdb.com/images/media/meals/1529446137.jpg", "category": "Vegetarian"}, {"id": "th_53370", "name": "Egg Foo Young", "thumb": "https://www.themealdb.com/images/media/meals/47y6ii1765658818.jpg", "category": "Seafood"}, {"id": "th_52951", "name": "General Tsos Chicken", "thumb": "https://www.themealdb.com/images/media/meals/1529444113.jpg", "category": "Chicken"}, {"id": "th_52954", "name": "Hot and Sour Soup", "thumb": "https://www.themealdb.com/images/media/meals/1529445893.jpg", "category": "Pork"}, {"id": "th_52945", "name": "Kung Pao Chicken", "thumb": "https://www.themealdb.com/images/media/meals/1525872624.jpg", "category": "Chicken"}, {"id": "th_52946", "name": "Kung Po Prawns", "thumb": "https://www.themealdb.com/images/media/meals/1525873040.jpg", "category": "Seafood"}, {"id": "th_52947", "name": "Ma Po Tofu", "thumb": "https://www.themealdb.com/images/media/meals/1525874812.jpg", "category": "Beef"}, {"id": "th_53377", "name": "Napa Cabbage with Dried Shrimp", "thumb": "https://www.themealdb.com/images/media/meals/9nh4dl1766435484.jpg", "category": "Seafood"}, {"id": "th_53383", "name": "Ramen Noodles with Boiled Egg", "thumb": "https://www.themealdb.com/images/media/meals/ip5xtp1769779958.jpg", "category": "Miscellaneous"}, {"id": "th_53378", "name": "Sesame Cucumber Salad", "thumb": "https://www.themealdb.com/images/media/meals/93iok31766436070.jpg", "category": "Side"}, {"id": "th_52953", "name": "Shrimp Chow Fun", "thumb": "https://www.themealdb.com/images/media/meals/1529445434.jpg", "category": "Seafood"}, {"id": "th_53375", "name": "Shrimp With Snow Peas", "thumb": "https://www.themealdb.com/images/media/meals/fpl3mv1766433431.jpg", "category": "Seafood"}, {"id": "th_53374", "name": "Sichuan Eggplant", "thumb": "https://www.themealdb.com/images/media/meals/1oz4nb1765687990.jpg", "category": "Vegetarian"}, {"id": "th_53371", "name": "Sichuan Style Stir-Fried Chinese Long Beans", "thumb": "https://www.themealdb.com/images/media/meals/i0610h1765659464.jpg", "category": "Vegetarian"}, {"id": "th_53369", "name": "Silken Tofu with Sesame Soy Sauce", "thumb": "https://www.themealdb.com/images/media/meals/j9nray1765657692.jpg", "category": "Vegetarian"}, {"id": "th_53368", "name": "Singapore Noodles with Shrimp", "thumb": "https://www.themealdb.com/images/media/meals/f3cxnc1765656994.jpg", "category": "Seafood"}, {"id": "th_53376", "name": "Sweet and Sour Chicken", "thumb": "https://www.themealdb.com/images/media/meals/arzs741766434335.jpg", "category": "Chicken"}, {"id": "th_52949", "name": "Sweet and Sour Pork", "thumb": "https://www.themealdb.com/images/media/meals/1529442316.jpg", "category": "Pork"}, {"id": "th_52950", "name": "Szechuan Beef", "thumb": "https://www.themealdb.com/images/media/meals/1529443236.jpg", "category": "Beef"}, {"id": "th_52948", "name": "Wontons", "thumb": "https://www.themealdb.com/images/media/meals/1525876468.jpg", "category": "Pork"}], "Jamaican": [{"id": "th_52940", "name": "Brown Stew Chicken", "thumb": "https://www.themealdb.com/images/media/meals/sypxpx1515365095.jpg", "category": "Chicken"}, {"id": "th_52939", "name": "Callaloo Jamaican Style", "thumb": "https://www.themealdb.com/images/media/meals/ussyxw1515364536.jpg", "category": "Miscellaneous"}, {"id": "th_53361", "name": "Callaloo and SaltFish", "thumb": "https://www.themealdb.com/images/media/meals/73o3vq1765317873.jpg", "category": "Side"}, {"id": "th_53360", "name": "Caribbean Tamarind balls", "thumb": "https://www.themealdb.com/images/media/meals/z1hz7z1765316430.jpg", "category": "Dessert"}, {"id": "th_53350", "name": "Corned Beef and Cabbage – Jamaican Style", "thumb": "https://www.themealdb.com/images/media/meals/kdz63q1764793442.jpg", "category": "Beef"}, {"id": "th_52944", "name": "Escovitch Fish", "thumb": "https://www.themealdb.com/images/media/meals/1520084413.jpg", "category": "Seafood"}, {"id": "th_53346", "name": "Grape Nut Ice Cream", "thumb": "https://www.themealdb.com/images/media/meals/1xscby1764790242.jpg", "category": "Dessert"}, {"id": "th_53351", "name": "Jamaican Banana Fritters", "thumb": "https://www.themealdb.com/images/media/meals/ul2uy31764794321.jpg", "category": "Dessert"}, {"id": "th_52938", "name": "Jamaican Beef Patties", "thumb": "https://www.themealdb.com/images/media/meals/wsqqsw1515364068.jpg", "category": "Beef"}, {"id": "th_53353", "name": "Jamaican Boiled Dumplings", "thumb": "https://www.themealdb.com/images/media/meals/tsdbcq1764795636.jpg", "category": "Side"}, {"id": "th_53363", "name": "Jamaican Cornmeal Porridge", "thumb": "https://www.themealdb.com/images/media/meals/sng9bm1765320170.jpg", "category": "Breakfast"}, {"id": "th_53345", "name": "Jamaican Curry Chicken Recipe", "thumb": "https://www.themealdb.com/images/media/meals/o5fuq51764789643.jpg", "category": "Chicken"}, {"id": "th_53354", "name": "Jamaican Curry Goat", "thumb": "https://www.themealdb.com/images/media/meals/uc9qp11764796575.jpg", "category": "Goat"}, {"id": "th_53362", "name": "Jamaican Curry Shrimp Recipe", "thumb": "https://www.themealdb.com/images/media/meals/n7h5zs1765318909.jpg", "category": "Seafood"}, {"id": "th_53355", "name": "Jamaican Festival (Sweet Dumpling)", "thumb": "https://www.themealdb.com/images/media/meals/g6xb8m1764875029.jpg", "category": "Side"}, {"id": "th_53356", "name": "Jamaican Fried Dumplings", "thumb": "https://www.themealdb.com/images/media/meals/dd7t4d1764877271.jpg", "category": "Side"}, {"id": "th_53352", "name": "Jamaican Instant Pot Rice and Beans", "thumb": "https://www.themealdb.com/images/media/meals/11bvtm1764795135.jpg", "category": "Vegetarian"}, {"id": "th_53349", "name": "Jamaican Pepper Shrimp", "thumb": "https://www.themealdb.com/images/media/meals/bx07m71764792853.jpg", "category": "Seafood"}, {"id": "th_53357", "name": "Jamaican Rice and Peas", "thumb": "https://www.themealdb.com/images/media/meals/pkyvrn1764878267.jpg", "category": "Vegetarian"}, {"id": "th_53348", "name": "Jamaican Spice Bun Recipe", "thumb": "https://www.themealdb.com/images/media/meals/08c5f41764791918.jpg", "category": "Dessert"}, {"id": "th_53364", "name": "Jamaican Steamed Cabbage", "thumb": "https://www.themealdb.com/images/media/meals/paejva1765321314.jpg", "category": "Side"}, {"id": "th_53344", "name": "Jamaican Sweet Potato Pudding", "thumb": "https://www.themealdb.com/images/media/meals/xj9sa81764788866.jpg", "category": "Dessert"}, {"id": "th_52937", "name": "Jerk chicken with rice & peas", "thumb": "https://www.themealdb.com/images/media/meals/tytyxu1515363282.jpg", "category": "Chicken"}, {"id": "th_53347", "name": "No-Churn Rum Raisin Ice Cream", "thumb": "https://www.themealdb.com/images/media/meals/s9qyzd1764790772.jpg", "category": "Dessert"}, {"id": "th_52943", "name": "Oxtail with broad beans", "thumb": "https://www.themealdb.com/images/media/meals/1520083578.jpg", "category": "Beef"}, {"id": "th_52941", "name": "Red Peas Soup", "thumb": "https://www.themealdb.com/images/media/meals/sqpqtp1515365614.jpg", "category": "Beef"}, {"id": "th_52936", "name": "Saltfish and Ackee", "thumb": "https://www.themealdb.com/images/media/meals/vytypy1511883765.jpg", "category": "Seafood"}], "Polish": [{"id": "th_53307", "name": "Beetroot & red cabbage sauerkraut", "thumb": "https://www.themealdb.com/images/media/meals/ra2k8a1764365055.jpg", "category": "Vegetarian"}, {"id": "th_53018", "name": "Bigos (Hunters Stew)", "thumb": "https://www.themealdb.com/images/media/meals/md8w601593348504.jpg", "category": "Pork"}, {"id": "th_53300", "name": "Bigos (Polish hunter's stew)", "thumb": "https://www.themealdb.com/images/media/meals/fl4brj1764361323.jpg", "category": "Beef"}, {"id": "th_53305", "name": "Braised stuffed cabbage", "thumb": "https://www.themealdb.com/images/media/meals/z267f71764364072.jpg", "category": "Vegetarian"}, {"id": "th_53310", "name": "Challah", "thumb": "https://www.themealdb.com/images/media/meals/fm01ky1764366365.jpg", "category": "Side"}, {"id": "th_53309", "name": "Cucumber & fennel salad", "thumb": "https://www.themealdb.com/images/media/meals/ei21r61764365935.jpg", "category": "Vegetarian"}, {"id": "th_53021", "name": "Golabki (cabbage roll)", "thumb": "https://www.themealdb.com/images/media/meals/q8sp3j1593349686.jpg", "category": "Beef"}, {"id": "th_53304", "name": "Mini bundt cakes", "thumb": "https://www.themealdb.com/images/media/meals/tzt3it1764363293.jpg", "category": "Dessert"}, {"id": "th_53017", "name": "Paszteciki (Polish Pasties)", "thumb": "https://www.themealdb.com/images/media/meals/c9a3l31593261890.jpg", "category": "Beef"}, {"id": "th_53292", "name": "Piernik (Polish gingerbread)", "thumb": "https://www.themealdb.com/images/media/meals/kwmdk41764120884.jpg", "category": "Dessert"}, {"id": "th_53019", "name": "Pierogi (Polish Dumplings)", "thumb": "https://www.themealdb.com/images/media/meals/45xxr21593348847.jpg", "category": "Side"}, {"id": "th_53293", "name": "Pistachio cake", "thumb": "https://www.themealdb.com/images/media/meals/xvgpng1764121726.jpg", "category": "Dessert"}, {"id": "th_53295", "name": "Polish chocolate & walnut cake", "thumb": "https://www.themealdb.com/images/media/meals/e8ihjp1764123021.jpg", "category": "Dessert"}, {"id": "th_53298", "name": "Polish doughnuts (Pączki)", "thumb": "https://www.themealdb.com/images/media/meals/x6jqog1764359857.jpg", "category": "Dessert"}, {"id": "th_53299", "name": "Polish patties (kotlety)", "thumb": "https://www.themealdb.com/images/media/meals/vvn5f71764360273.jpg", "category": "Side"}, {"id": "th_53022", "name": "Polskie Nalesniki (Polish Pancakes)", "thumb": "https://www.themealdb.com/images/media/meals/58bkyo1593350017.jpg", "category": "Dessert"}, {"id": "th_53297", "name": "Pomegranate salad", "thumb": "https://www.themealdb.com/images/media/meals/fqpqml1764359125.jpg", "category": "Vegetarian"}, {"id": "th_53301", "name": "Pork & sauerkraut goulash", "thumb": "https://www.themealdb.com/images/media/meals/cyuhwp1764362103.jpg", "category": "Pork"}, {"id": "th_53306", "name": "Pork rib bortsch", "thumb": "https://www.themealdb.com/images/media/meals/om5hsl1764364721.jpg", "category": "Pork"}, {"id": "th_53303", "name": "Raspberry mousse", "thumb": "https://www.themealdb.com/images/media/meals/v5jrnn1764362830.jpg", "category": "Dessert"}, {"id": "th_53024", "name": "Rogaliki (Polish Croissant Cookies)", "thumb": "https://www.themealdb.com/images/media/meals/7mxnzz1593350801.jpg", "category": "Dessert"}, {"id": "th_53020", "name": "Rosol (Polish Chicken Soup)", "thumb": "https://www.themealdb.com/images/media/meals/lx1kkj1593349302.jpg", "category": "Chicken"}, {"id": "th_53308", "name": "Rye bread", "thumb": "https://www.themealdb.com/images/media/meals/lmc6r51764365554.jpg", "category": "Side"}, {"id": "th_53296", "name": "Sauerkraut pierogi", "thumb": "https://www.themealdb.com/images/media/meals/ckbx1h1764123606.jpg", "category": "Vegetarian"}, {"id": "th_53023", "name": "Sledz w Oleju (Polish Herrings)", "thumb": "https://www.themealdb.com/images/media/meals/7ttta31593350374.jpg", "category": "Seafood"}, {"id": "th_53302", "name": "Slow-roasted ham with lemon, garlic & sage", "thumb": "https://www.themealdb.com/images/media/meals/w36ets1764362474.jpg", "category": "Pork"}, {"id": "th_53294", "name": "Zapiekanki", "thumb": "https://www.themealdb.com/images/media/meals/72lmpt1764122511.jpg", "category": "Pork"}], "Thai": [{"id": "th_53193", "name": "Drunken noodles (pad kee mao)", "thumb": "https://www.themealdb.com/images/media/meals/2wx8cm1763373419.jpg", "category": "Beef"}, {"id": "th_53211", "name": "Lemongrass beef stew with noodles", "thumb": "https://www.themealdb.com/images/media/meals/ntafxw1763586291.jpg", "category": "Beef"}, {"id": "th_52827", "name": "Massaman Beef curry", "thumb": "https://www.themealdb.com/images/media/meals/tvttqv1504640475.jpg", "category": "Beef"}, {"id": "th_52774", "name": "Pad See Ew", "thumb": "https://www.themealdb.com/images/media/meals/uuuspp1468263334.jpg", "category": "Chicken"}, {"id": "th_53191", "name": "Pad Thai", "thumb": "https://www.themealdb.com/images/media/meals/rg9ze01763479093.jpg", "category": "Seafood"}, {"id": "th_53192", "name": "Panang chicken curry (kaeng panang gai)", "thumb": "https://www.themealdb.com/images/media/meals/0dhtwr1763371444.jpg", "category": "Chicken"}, {"id": "th_53200", "name": "Prawn stir-fry", "thumb": "https://www.themealdb.com/images/media/meals/96lt871763480970.jpg", "category": "Seafood"}, {"id": "th_53204", "name": "Red curry chicken kebabs", "thumb": "https://www.themealdb.com/images/media/meals/prjve31763486864.jpg", "category": "Chicken"}, {"id": "th_53209", "name": "Spicy Thai prawn noodles", "thumb": "https://www.themealdb.com/images/media/meals/568t931763584227.jpg", "category": "Seafood"}, {"id": "th_53201", "name": "Stir-fried chicken with chillies & basil", "thumb": "https://www.themealdb.com/images/media/meals/el64dy1763483009.jpg", "category": "Chicken"}, {"id": "th_52814", "name": "Thai Green Curry", "thumb": "https://www.themealdb.com/images/media/meals/sstssx1487349585.jpg", "category": "Chicken"}, {"id": "th_53199", "name": "Thai beef stir-fry", "thumb": "https://www.themealdb.com/images/media/meals/kyuxew1763479470.jpg", "category": "Beef"}, {"id": "th_53206", "name": "Thai chicken cakes with sweet chilli sauce", "thumb": "https://www.themealdb.com/images/media/meals/6s3i3p1763488540.jpg", "category": "Chicken"}, {"id": "th_53208", "name": "Thai coconut & veg broth", "thumb": "https://www.themealdb.com/images/media/meals/4k8nzy1763583384.jpg", "category": "Vegetarian"}, {"id": "th_53195", "name": "Thai curry noodle soup", "thumb": "https://www.themealdb.com/images/media/meals/118oj61763423896.jpg", "category": "Seafood"}, {"id": "th_53212", "name": "Thai drumsticks", "thumb": "https://www.themealdb.com/images/media/meals/ittake1763586925.jpg", "category": "Chicken"}, {"id": "th_53198", "name": "Thai fried rice with prawns & peas", "thumb": "https://www.themealdb.com/images/media/meals/hblwvg1763478203.jpg", "category": "Seafood"}, {"id": "th_53214", "name": "Thai green chicken soup", "thumb": "https://www.themealdb.com/images/media/meals/7kb44y1763589084.jpg", "category": "Chicken"}, {"id": "th_53197", "name": "Thai pork & peanut curry", "thumb": "https://www.themealdb.com/images/media/meals/snmtd61763426568.jpg", "category": "Pork"}, {"id": "th_53205", "name": "Thai prawn curry", "thumb": "https://www.themealdb.com/images/media/meals/qqlwv91763501559.jpg", "category": "Seafood"}, {"id": "th_53210", "name": "Thai pumpkin soup", "thumb": "https://www.themealdb.com/images/media/meals/1brbso1763585098.jpg", "category": "Vegetarian"}, {"id": "th_53203", "name": "Thai rice noodle salad", "thumb": "https://www.themealdb.com/images/media/meals/6g3rso1763486069.jpg", "category": "Vegetarian"}, {"id": "th_53213", "name": "Thai-style fish broth with greens", "thumb": "https://www.themealdb.com/images/media/meals/a2ec961763587756.jpg", "category": "Seafood"}, {"id": "th_53202", "name": "Thai-style steamed fish", "thumb": "https://www.themealdb.com/images/media/meals/yx8j1i1763484612.jpg", "category": "Seafood"}, {"id": "th_53207", "name": "Tom kha gai", "thumb": "https://www.themealdb.com/images/media/meals/ol2xxt1763582263.jpg", "category": "Chicken"}, {"id": "th_53196", "name": "Tom yum (hot & sour) soup with prawns", "thumb": "https://www.themealdb.com/images/media/meals/9c5nlx1763424766.jpg", "category": "Seafood"}, {"id": "th_53194", "name": "Tom yum soup with prawns", "thumb": "https://www.themealdb.com/images/media/meals/l50vz41763422681.jpg", "category": "Seafood"}], "Vietnamese": [{"id": "th_53239", "name": "Bang bang prawn salad", "thumb": "https://www.themealdb.com/images/media/meals/4xcfai1763765676.jpg", "category": "Seafood"}, {"id": "th_53242", "name": "Barbecue pork buns", "thumb": "https://www.themealdb.com/images/media/meals/tzsy461763769901.jpg", "category": "Pork"}, {"id": "th_52997", "name": "Beef Banh Mi Bowls with Sriracha Mayo, Carrot & Pickled Cucumber", "thumb": "https://www.themealdb.com/images/media/meals/z0ageb1583189517.jpg", "category": "Beef"}, {"id": "th_53238", "name": "Beef pho", "thumb": "https://www.themealdb.com/images/media/meals/pbzcrx1763765096.jpg", "category": "Beef"}, {"id": "th_53245", "name": "Noodle bowl salad", "thumb": "https://www.themealdb.com/images/media/meals/zry07j1763779321.jpg", "category": "Seafood"}, {"id": "th_53244", "name": "Prawn & noodle salad with crispy shallots", "thumb": "https://www.themealdb.com/images/media/meals/0iryz91763778419.jpg", "category": "Seafood"}, {"id": "th_53230", "name": "Purple sprouting broccoli tempura with nuoc cham", "thumb": "https://www.themealdb.com/images/media/meals/xnv4wf1763756529.jpg", "category": "Miscellaneous"}, {"id": "th_53227", "name": "Rice paper dumplings", "thumb": "https://www.themealdb.com/images/media/meals/sfahy01763752319.jpg", "category": "Pork"}, {"id": "th_53234", "name": "Salmon noodle soup", "thumb": "https://www.themealdb.com/images/media/meals/ikizdm1763760862.jpg", "category": "Seafood"}, {"id": "th_53248", "name": "Salmon noodle wraps", "thumb": "https://www.themealdb.com/images/media/meals/prrirc1763781360.jpg", "category": "Seafood"}, {"id": "th_53233", "name": "Salt & pepper squid", "thumb": "https://www.themealdb.com/images/media/meals/yxiilf1763759428.jpg", "category": "Seafood"}, {"id": "th_53247", "name": "Sea bass with sizzled ginger, chilli & spring onions", "thumb": "https://www.themealdb.com/images/media/meals/tqd7s21763780609.jpg", "category": "Seafood"}, {"id": "th_53229", "name": "Steak & Vietnamese noodle salad", "thumb": "https://www.themealdb.com/images/media/meals/st9shl1763755808.jpg", "category": "Beef"}, {"id": "th_53246", "name": "Tangy carrot, cabbage & onion salad", "thumb": "https://www.themealdb.com/images/media/meals/dbazbg1763779999.jpg", "category": "Vegetarian"}, {"id": "th_53240", "name": "Tofu, greens & cashew stir-fry", "thumb": "https://www.themealdb.com/images/media/meals/minfsc1763766806.jpg", "category": "Vegetarian"}, {"id": "th_53249", "name": "Turkey Bánh mì", "thumb": "https://www.themealdb.com/images/media/meals/1wj8w31763781990.jpg", "category": "Miscellaneous"}, {"id": "th_53251", "name": "Turkish lahmacun", "thumb": "https://www.themealdb.com/images/media/meals/tqd3ac1763786065.jpg", "category": "Beef"}, {"id": "th_53250", "name": "Vegan banh mi", "thumb": "https://www.themealdb.com/images/media/meals/sonirb1763782831.jpg", "category": "Vegan"}, {"id": "th_52828", "name": "Vietnamese Grilled Pork (bun-thit-nuong)", "thumb": "https://www.themealdb.com/images/media/meals/qqwypw1504642429.jpg", "category": "Pork"}, {"id": "th_53228", "name": "Vietnamese caramel trout", "thumb": "https://www.themealdb.com/images/media/meals/p02vq41763754350.jpg", "category": "Seafood"}, {"id": "th_53232", "name": "Vietnamese chicken salad", "thumb": "https://www.themealdb.com/images/media/meals/pk8wtn1763758591.jpg", "category": "Chicken"}, {"id": "th_53231", "name": "Vietnamese lamb shanks with sweet potatoes", "thumb": "https://www.themealdb.com/images/media/meals/7xte3u1763757761.jpg", "category": "Lamb"}, {"id": "th_53237", "name": "Vietnamese pork salad", "thumb": "https://www.themealdb.com/images/media/meals/g7jomp1763763994.jpg", "category": "Pork"}, {"id": "th_53243", "name": "Vietnamese prawn spiralized rolls", "thumb": "https://www.themealdb.com/images/media/meals/9r2xrg1763771238.jpg", "category": "Seafood"}, {"id": "th_53241", "name": "Vietnamese veg parcels", "thumb": "https://www.themealdb.com/images/media/meals/f698g91763768731.jpg", "category": "Vegetarian"}, {"id": "th_53235", "name": "Vietnamese-style caramel pork", "thumb": "https://www.themealdb.com/images/media/meals/4mzt101763761546.jpg", "category": "Pork"}, {"id": "th_53236", "name": "Vietnamese-style veggie hotpot", "thumb": "https://www.themealdb.com/images/media/meals/4uje7l1763762276.jpg", "category": "Vegetarian"}], "Canadian": [{"id": "th_52928", "name": "BeaverTails", "thumb": "https://www.themealdb.com/images/media/meals/ryppsv1511815505.jpg", "category": "Dessert"}, {"id": "th_52965", "name": "Breakfast Potatoes", "thumb": "https://www.themealdb.com/images/media/meals/1550441882.jpg", "category": "Breakfast"}, {"id": "th_52923", "name": "Canadian Butter Tarts", "thumb": "https://www.themealdb.com/images/media/meals/wpputp1511812960.jpg", "category": "Dessert"}, {"id": "th_53343", "name": "Classic Tourtière", "thumb": "https://www.themealdb.com/images/media/meals/0sd7ac1764787957.jpg", "category": "Beef"}, {"id": "th_53338", "name": "Date squares", "thumb": "https://www.themealdb.com/images/media/meals/u4scbo1764446514.jpg", "category": "Dessert"}, {"id": "th_53342", "name": "Figgy Duff", "thumb": "https://www.themealdb.com/images/media/meals/kzi6p51764787198.jpg", "category": "Dessert"}, {"id": "th_53341", "name": "Flapper Pie", "thumb": "https://www.themealdb.com/images/media/meals/6ht8141764786479.jpg", "category": "Dessert"}, {"id": "th_53340", "name": "Hodge Podge", "thumb": "https://www.themealdb.com/images/media/meals/xihv0c1764447887.jpg", "category": "Vegetarian"}, {"id": "th_53339", "name": "Jam jam cookies", "thumb": "https://www.themealdb.com/images/media/meals/sktequ1764447186.jpg", "category": "Dessert"}, {"id": "th_53335", "name": "Jiggs Dinner", "thumb": "https://www.themealdb.com/images/media/meals/z1tfnw1764443171.jpg", "category": "Beef"}, {"id": "th_53336", "name": "Molasses Baked Beans", "thumb": "https://www.themealdb.com/images/media/meals/9tddhg1764443699.jpg", "category": "Vegetarian"}, {"id": "th_52927", "name": "Montreal Smoked Meat", "thumb": "https://www.themealdb.com/images/media/meals/uttupv1511815050.jpg", "category": "Beef"}, {"id": "th_52924", "name": "Nanaimo Bars", "thumb": "https://www.themealdb.com/images/media/meals/vwuprt1511813703.jpg", "category": "Dessert"}, {"id": "th_52930", "name": "Pate Chinois", "thumb": "https://www.themealdb.com/images/media/meals/yyrrxr1511816289.jpg", "category": "Beef"}, {"id": "th_52932", "name": "Pouding chomeur", "thumb": "https://www.themealdb.com/images/media/meals/yqqqwu1511816912.jpg", "category": "Dessert"}, {"id": "th_52804", "name": "Poutine", "thumb": "https://www.themealdb.com/images/media/meals/uuyrrx1487327597.jpg", "category": "Miscellaneous"}, {"id": "th_52933", "name": "Rappie Pie", "thumb": "https://www.themealdb.com/images/media/meals/ruwpww1511817242.jpg", "category": "Chicken"}, {"id": "th_53337", "name": "Saskatoon Pie", "thumb": "https://www.themealdb.com/images/media/meals/5xdrkw1764444472.jpg", "category": "Dessert"}, {"id": "th_52925", "name": "Split Pea Soup", "thumb": "https://www.themealdb.com/images/media/meals/xxtsvx1511814083.jpg", "category": "Side"}, {"id": "th_52931", "name": "Sugar Pie", "thumb": "https://www.themealdb.com/images/media/meals/yrstur1511816601.jpg", "category": "Dessert"}, {"id": "th_52929", "name": "Timbits", "thumb": "https://www.themealdb.com/images/media/meals/txsupu1511815755.jpg", "category": "Dessert"}, {"id": "th_52926", "name": "Tourtiere", "thumb": "https://www.themealdb.com/images/media/meals/ytpstt1511814614.jpg", "category": "Pork"}], "Italian": [{"id": "th_52961", "name": "Budino Di Ricotta", "thumb": "https://www.themealdb.com/images/media/meals/1549542877.jpg", "category": "Dessert"}, {"id": "th_52796", "name": "Chicken Alfredo Primavera", "thumb": "https://www.themealdb.com/images/media/meals/syqypv1486981727.jpg", "category": "Chicken"}, {"id": "th_52839", "name": "Chilli prawn linguine", "thumb": "https://www.themealdb.com/images/media/meals/usywpp1511189717.jpg", "category": "Pasta"}, {"id": "th_53064", "name": "Fettuccine Alfredo", "thumb": "https://www.themealdb.com/images/media/meals/0jv5gx1661040802.jpg", "category": "Pasta"}, {"id": "th_52835", "name": "Fettucine alfredo", "thumb": "https://www.themealdb.com/images/media/meals/uquqtu1511178042.jpg", "category": "Pasta"}, {"id": "th_52844", "name": "Lasagne", "thumb": "https://www.themealdb.com/images/media/meals/wtsvxx1511296896.jpg", "category": "Pasta"}, {"id": "th_52777", "name": "Mediterranean Pasta Salad", "thumb": "https://www.themealdb.com/images/media/meals/wvqpwt1468339226.jpg", "category": "Seafood"}, {"id": "th_52810", "name": "Osso Buco alla Milanese", "thumb": "https://www.themealdb.com/images/media/meals/wwuqvt1487345467.jpg", "category": "Miscellaneous"}, {"id": "th_52837", "name": "Pilchard puttanesca", "thumb": "https://www.themealdb.com/images/media/meals/vvtvtr1511180578.jpg", "category": "Pasta"}, {"id": "th_53014", "name": "Pizza Express Margherita", "thumb": "https://www.themealdb.com/images/media/meals/x0lk931587671540.jpg", "category": "Miscellaneous"}, {"id": "th_52780", "name": "Potato Gratin with Chicken", "thumb": "https://www.themealdb.com/images/media/meals/qwrtut1468418027.jpg", "category": "Chicken"}, {"id": "th_52811", "name": "Ribollita", "thumb": "https://www.themealdb.com/images/media/meals/xrrwpx1487347049.jpg", "category": "Vegetarian"}, {"id": "th_52783", "name": "Rigatoni with fennel sausage sauce", "thumb": "https://www.themealdb.com/images/media/meals/qtqvys1468573168.jpg", "category": "Lamb"}, {"id": "th_52823", "name": "Salmon Prawn Risotto", "thumb": "https://www.themealdb.com/images/media/meals/xxrxux1503070723.jpg", "category": "Seafood"}, {"id": "th_52770", "name": "Spaghetti Bolognese", "thumb": "https://www.themealdb.com/images/media/meals/sutysw1468247559.jpg", "category": "Beef"}, {"id": "th_52982", "name": "Spaghetti alla Carbonara", "thumb": "https://www.themealdb.com/images/media/meals/llcbn01574260722.jpg", "category": "Pasta"}, {"id": "th_52771", "name": "Spicy Arrabiata Penne", "thumb": "https://www.themealdb.com/images/media/meals/ustsqw1468250014.jpg", "category": "Vegetarian"}, {"id": "th_52849", "name": "Spinach & Ricotta Cannelloni", "thumb": "https://www.themealdb.com/images/media/meals/wspuvp1511303478.jpg", "category": "Vegetarian"}, {"id": "th_52866", "name": "Squash linguine", "thumb": "https://www.themealdb.com/images/media/meals/wxswxy1511452625.jpg", "category": "Vegetarian"}, {"id": "th_52775", "name": "Vegan Lasagna", "thumb": "https://www.themealdb.com/images/media/meals/rvxxuy1468312893.jpg", "category": "Vegan"}, {"id": "th_52838", "name": "Venetian Duck Ragu", "thumb": "https://www.themealdb.com/images/media/meals/qvrwpt1511181864.jpg", "category": "Pasta"}], "Norway": [{"id": "th_53127", "name": "Authentic Norwegian Kransekake", "thumb": "https://www.themealdb.com/images/media/meals/yk78uc1763075719.jpg", "category": "Dessert"}, {"id": "th_53126", "name": "Brun Lapskaus (Norwegian Beef Vegetable Stew)", "thumb": "https://www.themealdb.com/images/media/meals/6vi2cv1763075785.jpg", "category": "Beef"}, {"id": "th_53116", "name": "Cinnamon buns", "thumb": "https://www.themealdb.com/images/media/meals/as88dq1762772486.jpg", "category": "Dessert"}, {"id": "th_53122", "name": "Fiskesuppe (Creamy Norwegian Fish Soup)", "thumb": "https://www.themealdb.com/images/media/meals/raqjbj1762773035.jpg", "category": "Seafood"}, {"id": "th_53131", "name": "Fyrstekake – Norwegian Prince Cake", "thumb": "https://www.themealdb.com/images/media/meals/9zqrod1763075574.jpg", "category": "Dessert"}, {"id": "th_53123", "name": "Fårikål (Norwegian National Dish)", "thumb": "https://www.themealdb.com/images/media/meals/ttfxxn1762773067.jpg", "category": "Lamb"}, {"id": "th_53125", "name": "Karbonader (Lean Beef Patties) with Caramelized Onions", "thumb": "https://www.themealdb.com/images/media/meals/0bpjb11763075817.jpg", "category": "Beef"}, {"id": "th_53128", "name": "Kvæfjord Cake “Verdens Beste” (World’s Best Cake)", "thumb": "https://www.themealdb.com/images/media/meals/gdn1ot1763075684.jpg", "category": "Dessert"}, {"id": "th_53132", "name": "Mazariner – Scandinavian Almond Tartlets", "thumb": "https://www.themealdb.com/images/media/meals/uh1n5u1763075545.jpg", "category": "Dessert"}, {"id": "th_53117", "name": "Nordic smørrebrød with asparagus and horseradish cream", "thumb": "https://www.themealdb.com/images/media/meals/8a8fu01762772651.jpg", "category": "Vegetarian"}, {"id": "th_53129", "name": "Norwegian Krumkake", "thumb": "https://www.themealdb.com/images/media/meals/z9g8011763075640.jpg", "category": "Dessert"}, {"id": "th_53121", "name": "Norwegian Potato Lefse", "thumb": "https://www.themealdb.com/images/media/meals/hxcuj01762772827.jpg", "category": "Side"}, {"id": "th_53124", "name": "Raspeballer (Norwegian Potato Dumplings)", "thumb": "https://www.themealdb.com/images/media/meals/hhm7xy1763075871.jpg", "category": "Pork"}, {"id": "th_53115", "name": "Red onion pickle", "thumb": "https://www.themealdb.com/images/media/meals/ppodrp1762325183.jpg", "category": "Vegan"}, {"id": "th_53118", "name": "Rømmegrøt – Norwegian Sour Cream Porridge", "thumb": "https://www.themealdb.com/images/media/meals/hyk47c1762772689.jpg", "category": "Breakfast"}, {"id": "th_53130", "name": "Suksessterte (Norwegian almond “success cake”)", "thumb": "https://www.themealdb.com/images/media/meals/de83k51763075604.jpg", "category": "Dessert"}, {"id": "th_53119", "name": "Tall Skoleboller", "thumb": "https://www.themealdb.com/images/media/meals/xihiu41762773169.jpg", "category": "Dessert"}], "India": [{"id": "th_52807", "name": "Baingan Bharta", "thumb": "https://www.themealdb.com/images/media/meals/urtpqw1487341253.jpg", "category": "Vegetarian"}, {"id": "th_53359", "name": "Beef Mandi", "thumb": "https://www.themealdb.com/images/media/meals/1nalo51765188375.jpg", "category": "Beef"}, {"id": "th_53076", "name": "Bread omelette", "thumb": "https://www.themealdb.com/images/media/meals/hqaejl1695738653.jpg", "category": "Breakfast"}, {"id": "th_52795", "name": "Chicken Handi", "thumb": "https://www.themealdb.com/images/media/meals/wyxwsp1486979827.jpg", "category": "Chicken"}, {"id": "th_53358", "name": "Chicken Mandi", "thumb": "https://www.themealdb.com/images/media/meals/er4d081765186828.jpg", "category": "Chicken"}, {"id": "th_52785", "name": "Dal fry", "thumb": "https://www.themealdb.com/images/media/meals/wuxrtu1483564410.jpg", "category": "Vegetarian"}, {"id": "th_52868", "name": "Kidney Bean Curry", "thumb": "https://www.themealdb.com/images/media/meals/sywrsu1511463066.jpg", "category": "Vegetarian"}, {"id": "th_52805", "name": "Lamb Biryani", "thumb": "https://www.themealdb.com/images/media/meals/xrttsx1487339558.jpg", "category": "Lamb"}, {"id": "th_52808", "name": "Lamb Rogan josh", "thumb": "https://www.themealdb.com/images/media/meals/vvstvq1487342592.jpg", "category": "Lamb"}, {"id": "th_52865", "name": "Matar Paneer", "thumb": "https://www.themealdb.com/images/media/meals/xxpqsy1511452222.jpg", "category": "Vegetarian"}, {"id": "th_52851", "name": "Nutty Chicken Curry", "thumb": "https://www.themealdb.com/images/media/meals/yxsurp1511304301.jpg", "category": "Chicken"}, {"id": "th_52809", "name": "Recheado Masala Fish", "thumb": "https://www.themealdb.com/images/media/meals/uwxusv1487344500.jpg", "category": "Seafood"}, {"id": "th_52964", "name": "Smoked Haddock Kedgeree", "thumb": "https://www.themealdb.com/images/media/meals/1550441275.jpg", "category": "Breakfast"}, {"id": "th_52806", "name": "Tandoori chicken", "thumb": "https://www.themealdb.com/images/media/meals/qptpvt1487339892.jpg", "category": "Chicken"}], "Australian": [{"id": "th_53111", "name": "Anzac biscuits", "thumb": "https://www.themealdb.com/images/media/meals/q47rkb1762324620.jpg", "category": "Dessert"}, {"id": "th_53099", "name": "Aussie Burgers", "thumb": "https://www.themealdb.com/images/media/meals/44bzep1761848278.jpg", "category": "Beef"}, {"id": "th_53107", "name": "Avocado dip with new potatoes", "thumb": "https://www.themealdb.com/images/media/meals/flrajf1762341295.jpg", "category": "Vegetarian"}, {"id": "th_53103", "name": "Barramundi with Moroccan spices", "thumb": "https://www.themealdb.com/images/media/meals/4o4wh11761848573.jpg", "category": "Seafood"}, {"id": "th_53100", "name": "Blueberry & lemon friands", "thumb": "https://www.themealdb.com/images/media/meals/e756bf1761848342.jpg", "category": "Dessert"}, {"id": "th_53101", "name": "Chocolate Coconut Squares", "thumb": "https://www.themealdb.com/images/media/meals/8oupz51761848432.jpg", "category": "Dessert"}, {"id": "th_53104", "name": "Lamingtons", "thumb": "https://www.themealdb.com/images/media/meals/j2n7vg1761848636.jpg", "category": "Dessert"}, {"id": "th_53109", "name": "Mini chilli beef pies", "thumb": "https://www.themealdb.com/images/media/meals/6sarfo1762340107.jpg", "category": "Beef"}, {"id": "th_53108", "name": "Quick salt & pepper squid", "thumb": "https://www.themealdb.com/images/media/meals/cp74zo1762341241.jpg", "category": "Seafood"}, {"id": "th_53105", "name": "Spiced smoky barbecued chicken", "thumb": "https://www.themealdb.com/images/media/meals/a08uqk1761848682.jpg", "category": "Chicken"}, {"id": "th_53102", "name": "Squid, chickpea & chorizo salad", "thumb": "https://www.themealdb.com/images/media/meals/wsu0rc1761848482.jpg", "category": "Seafood"}, {"id": "th_53110", "name": "Sticky Chicken", "thumb": "https://www.themealdb.com/images/media/meals/cj56fs1762340001.jpg", "category": "Chicken"}, {"id": "th_53106", "name": "Warm roast asparagus salad", "thumb": "https://www.themealdb.com/images/media/meals/ktsws11761998344.jpg", "category": "Pork"}], "Netherlands": [{"id": "th_53389", "name": "Apple Potato Mash (Hete bliksem) ", "thumb": "https://www.themealdb.com/images/media/meals/pa03n41777540582.jpg", "category": "Side"}, {"id": "th_53380", "name": "Apple cake", "thumb": "https://www.themealdb.com/images/media/meals/c0gmo31766594751.jpg", "category": "Dessert"}, {"id": "th_52979", "name": "Bitterballen (Dutch meatballs)", "thumb": "https://www.themealdb.com/images/media/meals/lhqev81565090111.jpg", "category": "Beef"}, {"id": "th_53385", "name": "Boterkoek (Dutch Butter Cake)", "thumb": "https://www.themealdb.com/images/media/meals/tkwxmv1777540463.jpg", "category": "Dessert"}, {"id": "th_53386", "name": "Dutch Apple Pie", "thumb": "https://www.themealdb.com/images/media/meals/zy4fs51777540384.jpg", "category": "Dessert"}, {"id": "th_53387", "name": "Dutch Spiced Breakfast Cake (Ontbijtkoek)", "thumb": "https://www.themealdb.com/images/media/meals/uwq8001777540502.jpg", "category": "Dessert"}, {"id": "th_53379", "name": "Dutch poffertjes (mini pancakes)", "thumb": "https://www.themealdb.com/images/media/meals/oaqz9f1766593912.jpg", "category": "Breakfast"}, {"id": "th_53382", "name": "Dutch stroopwafel", "thumb": "https://www.themealdb.com/images/media/meals/8cvkcz1766596315.jpg", "category": "Dessert"}, {"id": "th_53381", "name": "Gevulde speculaas", "thumb": "https://www.themealdb.com/images/media/meals/rw64di1766595573.jpg", "category": "Dessert"}, {"id": "th_52769", "name": "Kapsalon", "thumb": "https://www.themealdb.com/images/media/meals/sxysrt1468240488.jpg", "category": "Lamb"}, {"id": "th_53388", "name": "Runner Bean Mash (Snijbonen Stamppot)", "thumb": "https://www.themealdb.com/images/media/meals/urq5w21777540535.jpg", "category": "Side"}, {"id": "th_52981", "name": "Snert (Dutch Split Pea Soup)", "thumb": "https://www.themealdb.com/images/media/meals/9ptx0a1565090843.jpg", "category": "Side"}, {"id": "th_52980", "name": "Stamppot", "thumb": "https://www.themealdb.com/images/media/meals/hyarod1565090529.jpg", "category": "Pork"}], "Algerian": [{"id": "th_53284", "name": "Algerian Bouzgene Berber Bread with Roasted Pepper Sauce", "thumb": "https://www.themealdb.com/images/media/meals/se5vhk1764114880.jpg", "category": "Side"}, {"id": "th_53282", "name": "Algerian Carrots", "thumb": "https://www.themealdb.com/images/media/meals/o2cd4r1764113576.jpg", "category": "Side"}, {"id": "th_53288", "name": "Algerian Flafla (Bell Pepper Salad)", "thumb": "https://www.themealdb.com/images/media/meals/tbj1bs1764118062.jpg", "category": "Vegetarian"}, {"id": "th_53281", "name": "Algerian Kefta (Meatballs)", "thumb": "https://www.themealdb.com/images/media/meals/8rfd4q1764112993.jpg", "category": "Beef"}, {"id": "th_53290", "name": "Cheese Borek", "thumb": "https://www.themealdb.com/images/media/meals/oal8x31764119345.jpg", "category": "Side"}, {"id": "th_53289", "name": "Chorba Hamra bel Frik (Algerian Lamb, Tomato, and Freekeh Soup)", "thumb": "https://www.themealdb.com/images/media/meals/p9tebp1764118792.jpg", "category": "Lamb"}, {"id": "th_53283", "name": "Chtitha Batata (Algerian Potato Stew)", "thumb": "https://www.themealdb.com/images/media/meals/q8pu1k1764114334.jpg", "category": "Vegetarian"}, {"id": "th_53291", "name": "Cornes de Gazelle (Gazelle Horns)", "thumb": "https://www.themealdb.com/images/media/meals/0h1b7m1764120235.jpg", "category": "Dessert"}, {"id": "th_53285", "name": "Dziriat (Algerian Almond Tarts)", "thumb": "https://www.themealdb.com/images/media/meals/ne5wzp1764115568.jpg", "category": "Dessert"}, {"id": "th_53286", "name": "Khobz el Dar (Algerian Semolina Bread)", "thumb": "https://www.themealdb.com/images/media/meals/5u37fy1764116774.jpg", "category": "Side"}, {"id": "th_53280", "name": "Poulet Roti a l'Algerienne (Algerian Roast Chicken)", "thumb": "https://www.themealdb.com/images/media/meals/nlxald1764112200.jpg", "category": "Chicken"}, {"id": "th_53287", "name": "Tajine de Poulet aux Carottes et Patates Douces (Chicken and Sweet Potato Tagine)", "thumb": "https://www.themealdb.com/images/media/meals/d8bfyg1764117503.jpg", "category": "Chicken"}], "Saudi Arabian": [{"id": "th_53218", "name": "Chicken Shawarma with homemade garlic herb yoghurt sauce", "thumb": "https://www.themealdb.com/images/media/meals/hcg6l91763596970.jpg", "category": "Chicken"}, {"id": "th_53216", "name": "Knafeh", "thumb": "https://www.themealdb.com/images/media/meals/76nffj1763593933.jpg", "category": "Dessert"}, {"id": "th_53221", "name": "Mamoul (Eid biscuits)", "thumb": "https://www.themealdb.com/images/media/meals/35kejr1763599712.jpg", "category": "Dessert"}, {"id": "th_53223", "name": "Mutabbaq", "thumb": "https://www.themealdb.com/images/media/meals/i5o2b61763739053.jpg", "category": "Miscellaneous"}, {"id": "th_53224", "name": "Pistachio Kunafa Chocolate Cake and Cupcakes", "thumb": "https://www.themealdb.com/images/media/meals/yh3sg71763741307.jpg", "category": "Dessert"}, {"id": "th_53215", "name": "Shakshouka", "thumb": "https://www.themealdb.com/images/media/meals/crd1jz1763592990.jpg", "category": "Miscellaneous"}, {"id": "th_53219", "name": "Shakshuka Feta Cheese", "thumb": "https://www.themealdb.com/images/media/meals/wpkfin1763597958.jpg", "category": "Miscellaneous"}, {"id": "th_53226", "name": "Shawarma bread", "thumb": "https://www.themealdb.com/images/media/meals/i8l2fu1763742525.jpg", "category": "Side"}, {"id": "th_53217", "name": "Shawarma chuck roast wrap", "thumb": "https://www.themealdb.com/images/media/meals/swo87v1763595282.jpg", "category": "Beef"}, {"id": "th_53222", "name": "Vegetarian Shakshuka", "thumb": "https://www.themealdb.com/images/media/meals/eo0yfb1763600916.jpg", "category": "Vegetarian"}, {"id": "th_53225", "name": "Yemeni Lahsa (Elite Shakshuka)", "thumb": "https://www.themealdb.com/images/media/meals/30s7vf1763741844.jpg", "category": "Breakfast"}, {"id": "th_53220", "name": "kabse", "thumb": "https://www.themealdb.com/images/media/meals/utqnjv1763598650.jpg", "category": "Chicken"}], "Argentina": [{"id": "th_53138", "name": "Alfajores", "thumb": "https://www.themealdb.com/images/media/meals/a4kgf21763075288.jpg", "category": "Dessert"}, {"id": "th_53133", "name": "Asado", "thumb": "https://www.themealdb.com/images/media/meals/kgfh3q1763075438.jpg", "category": "Beef"}, {"id": "th_53141", "name": "Carbonada Criolla", "thumb": "https://www.themealdb.com/images/media/meals/8b2msz1763074897.jpg", "category": "Beef"}, {"id": "th_53136", "name": "Choripán", "thumb": "https://www.themealdb.com/images/media/meals/5i25sg1763075353.jpg", "category": "Pork"}, {"id": "th_53137", "name": "Dulce de Leche", "thumb": "https://www.themealdb.com/images/media/meals/jyjlhj1763075323.jpg", "category": "Dessert"}, {"id": "th_53134", "name": "Empanadas", "thumb": "https://www.themealdb.com/images/media/meals/q99te31763075494.jpg", "category": "Beef"}, {"id": "th_53139", "name": "Fainá", "thumb": "https://www.themealdb.com/images/media/meals/849jd81763075251.jpg", "category": "Side"}, {"id": "th_53146", "name": "Locro", "thumb": "https://www.themealdb.com/images/media/meals/5sgsob1763196284.jpg", "category": "Miscellaneous"}, {"id": "th_53140", "name": "Matambre a la Pizza", "thumb": "https://www.themealdb.com/images/media/meals/wf49qs1763075222.jpg", "category": "Beef"}, {"id": "th_53135", "name": "Milanesa", "thumb": "https://www.themealdb.com/images/media/meals/wdfa171763065079.jpg", "category": "Beef"}], "Venezuela": [{"id": "th_53334", "name": "Arepa Pabellón", "thumb": "https://www.themealdb.com/images/media/meals/13fg4j1764441982.jpg", "category": "Beef"}, {"id": "th_53329", "name": "Arepa pelua", "thumb": "https://www.themealdb.com/images/media/meals/jgl9qq1764437635.jpg", "category": "Beef"}, {"id": "th_53330", "name": "Cassava pizza", "thumb": "https://www.themealdb.com/images/media/meals/lrfdwz1764438393.jpg", "category": "Pork"}, {"id": "th_53331", "name": "Oatmeal pancakes", "thumb": "https://www.themealdb.com/images/media/meals/c400ok1764439058.jpg", "category": "Breakfast"}, {"id": "th_53333", "name": "Passion fruit mousse", "thumb": "https://www.themealdb.com/images/media/meals/gkcdpl1764441325.jpg", "category": "Dessert"}, {"id": "th_53325", "name": "Venezuelan Arepas", "thumb": "https://www.themealdb.com/images/media/meals/3hcy191764376285.jpg", "category": "Side"}, {"id": "th_53327", "name": "Venezuelan Coconut Chicken", "thumb": "https://www.themealdb.com/images/media/meals/z2sw3o1764378271.jpg", "category": "Chicken"}, {"id": "th_53326", "name": "Venezuelan Sancocho", "thumb": "https://www.themealdb.com/images/media/meals/8859m71764377470.jpg", "category": "Beef"}, {"id": "th_53328", "name": "Venezuelan Shredded Beef", "thumb": "https://www.themealdb.com/images/media/meals/mq27gf1764436795.jpg", "category": "Beef"}, {"id": "th_53332", "name": "Venezuelan turnovers", "thumb": "https://www.themealdb.com/images/media/meals/zjtfp31764440795.jpg", "category": "Side"}], "Japanese": [{"id": "th_52831", "name": "Chicken Karaage", "thumb": "https://www.themealdb.com/images/media/meals/tyywsw1505930373.jpg", "category": "Chicken"}, {"id": "th_52773", "name": "Honey Teriyaki Salmon", "thumb": "https://www.themealdb.com/images/media/meals/xxyupu1468262513.jpg", "category": "Seafood"}, {"id": "th_53034", "name": "Japanese Katsudon", "thumb": "https://www.themealdb.com/images/media/meals/d8f6qx1604182128.jpg", "category": "Pork"}, {"id": "th_53033", "name": "Japanese gohan rice", "thumb": "https://www.themealdb.com/images/media/meals/kw92t41604181871.jpg", "category": "Side"}, {"id": "th_52820", "name": "Katsu Chicken curry", "thumb": "https://www.themealdb.com/images/media/meals/vwrpps1503068729.jpg", "category": "Chicken"}, {"id": "th_53065", "name": "Sushi", "thumb": "https://www.themealdb.com/images/media/meals/g046bb1663960946.jpg", "category": "Seafood"}, {"id": "th_52772", "name": "Teriyaki Chicken Casserole", "thumb": "https://www.themealdb.com/images/media/meals/wvpsxx1468256321.jpg", "category": "Chicken"}, {"id": "th_53032", "name": "Tonkatsu pork", "thumb": "https://www.themealdb.com/images/media/meals/lwsnkl1604181187.jpg", "category": "Pork"}, {"id": "th_52871", "name": "Yaki Udon", "thumb": "https://www.themealdb.com/images/media/meals/wrustq1511475474.jpg", "category": "Vegetarian"}], "Uruguayan": [{"id": "th_53317", "name": "Beef Empanadas", "thumb": "https://www.themealdb.com/images/media/meals/dxpc7j1764370714.jpg", "category": "Beef"}, {"id": "th_53319", "name": "Chivito sandwich", "thumb": "https://www.themealdb.com/images/media/meals/j80gmw1764372176.jpg", "category": "Beef"}, {"id": "th_53063", "name": "Chivito uruguayo", "thumb": "https://www.themealdb.com/images/media/meals/n7qnkb1630444129.jpg", "category": "Beef"}, {"id": "th_53320", "name": "Chocolate alfajores", "thumb": "https://www.themealdb.com/images/media/meals/k9o0xr1764373018.jpg", "category": "Dessert"}, {"id": "th_53324", "name": "Chocolate empanadas", "thumb": "https://www.themealdb.com/images/media/meals/u9ezi21764375474.jpg", "category": "Dessert"}, {"id": "th_53322", "name": "Flan", "thumb": "https://www.themealdb.com/images/media/meals/0s80wo1764374393.jpg", "category": "Dessert"}, {"id": "th_53323", "name": "Postre Chajá", "thumb": "https://www.themealdb.com/images/media/meals/wii0591764375062.jpg", "category": "Dessert"}, {"id": "th_53318", "name": "Torta de fiambre", "thumb": "https://www.themealdb.com/images/media/meals/okl9cm1764371087.jpg", "category": "Pork"}, {"id": "th_53321", "name": "Vanilla alfajores", "thumb": "https://www.themealdb.com/images/media/meals/3wnyvh1764373818.jpg", "category": "Dessert"}], "Croatian": [{"id": "th_53060", "name": "Burek", "thumb": "https://www.themealdb.com/images/media/meals/tkxquw1628771028.jpg", "category": "Side"}, {"id": "th_53055", "name": "Cevapi Sausages", "thumb": "https://www.themealdb.com/images/media/meals/vc08jn1628769553.jpg", "category": "Beef"}, {"id": "th_53058", "name": "Croatian Bean Stew", "thumb": "https://www.themealdb.com/images/media/meals/tnwy8m1628770384.jpg", "category": "Beef"}, {"id": "th_53056", "name": "Croatian lamb peka", "thumb": "https://www.themealdb.com/images/media/meals/pn59o51628769837.jpg", "category": "Beef"}, {"id": "th_53061", "name": "Fresh sardines", "thumb": "https://www.themealdb.com/images/media/meals/nv5lf31628771380.jpg", "category": "Side"}, {"id": "th_53059", "name": "Mushroom soup with buckwheat", "thumb": "https://www.themealdb.com/images/media/meals/1ngcbf1628770793.jpg", "category": "Side"}, {"id": "th_53057", "name": "Traditional Croatian Goulash", "thumb": "https://www.themealdb.com/images/media/meals/n1hcou1628770088.jpg", "category": "Beef"}, {"id": "th_53062", "name": "Walnut Roll Gužvara", "thumb": "https://www.themealdb.com/images/media/meals/u9l7k81628771647.jpg", "category": "Dessert"}], "Egyptian": [{"id": "th_53031", "name": "Egyptian Fatteh", "thumb": "https://www.themealdb.com/images/media/meals/rlwcc51598734603.jpg", "category": "Beef"}, {"id": "th_53030", "name": "Feteer Meshaltet", "thumb": "https://www.themealdb.com/images/media/meals/9f4z6v1598734293.jpg", "category": "Side"}, {"id": "th_53025", "name": "Ful Medames", "thumb": "https://www.themealdb.com/images/media/meals/lvn2d51598732465.jpg", "category": "Vegetarian"}, {"id": "th_53027", "name": "Koshari", "thumb": "https://www.themealdb.com/images/media/meals/4er7mj1598733193.jpg", "category": "Vegetarian"}, {"id": "th_53029", "name": "Mulukhiyah", "thumb": "https://www.themealdb.com/images/media/meals/x372ug1598733932.jpg", "category": "Beef"}, {"id": "th_52963", "name": "Shakshuka", "thumb": "https://www.themealdb.com/images/media/meals/g373701551450225.jpg", "category": "Vegetarian"}, {"id": "th_53028", "name": "Shawarma", "thumb": "https://www.themealdb.com/images/media/meals/kcv6hj1598733479.jpg", "category": "Chicken"}, {"id": "th_53026", "name": "Tamiya", "thumb": "https://www.themealdb.com/images/media/meals/n3xxd91598732796.jpg", "category": "Vegetarian"}], "Filipino": [{"id": "th_53071", "name": "Beef Asado", "thumb": "https://www.themealdb.com/images/media/meals/pkopc31683207947.jpg", "category": "Beef"}, {"id": "th_53070", "name": "Beef Caldereta", "thumb": "https://www.themealdb.com/images/media/meals/41cxjh1683207682.jpg", "category": "Beef"}, {"id": "th_53068", "name": "Beef Mechado", "thumb": "https://www.themealdb.com/images/media/meals/cgl60b1683206581.jpg", "category": "Beef"}, {"id": "th_53069", "name": "Bistek", "thumb": "https://www.themealdb.com/images/media/meals/4pqimk1683207418.jpg", "category": "Beef"}, {"id": "th_53072", "name": "Crispy Eggplant", "thumb": "https://www.themealdb.com/images/media/meals/c7lzrl1683208757.jpg", "category": "Vegetarian"}, {"id": "th_53073", "name": "Eggplant Adobo", "thumb": "https://www.themealdb.com/images/media/meals/y7h0lq1683208991.jpg", "category": "Vegetarian"}, {"id": "th_53074", "name": "Grilled eggplant with coconut milk", "thumb": "https://www.themealdb.com/images/media/meals/bopa2i1683209167.jpg", "category": "Vegetarian"}, {"id": "th_53075", "name": "Tortang Talong", "thumb": "https://www.themealdb.com/images/media/meals/va668f1683209318.jpg", "category": "Vegetarian"}], "Greek": [{"id": "th_53011", "name": "Chicken Quinoa Greek Salad", "thumb": "https://www.themealdb.com/images/media/meals/k29viq1585565980.jpg", "category": "Chicken"}, {"id": "th_52764", "name": "Garides Saganaki", "thumb": "https://www.themealdb.com/images/media/meals/wuvryu1468232995.jpg", "category": "Seafood"}, {"id": "th_53012", "name": "Gigantes Plaki", "thumb": "https://www.themealdb.com/images/media/meals/b79r6f1585566277.jpg", "category": "Vegetarian"}, {"id": "th_53007", "name": "Honey Yogurt Cheesecake", "thumb": "https://www.themealdb.com/images/media/meals/y2irzl1585563479.jpg", "category": "Dessert"}, {"id": "th_53010", "name": "Lamb Tzatziki Burgers", "thumb": "https://www.themealdb.com/images/media/meals/k420tj1585565244.jpg", "category": "Lamb"}, {"id": "th_53009", "name": "Lamb and Lemon Souvlaki", "thumb": "https://www.themealdb.com/images/media/meals/rjhf741585564676.jpg", "category": "Lamb"}, {"id": "th_53006", "name": "Moussaka", "thumb": "https://www.themealdb.com/images/media/meals/ctg8jd1585563097.jpg", "category": "Beef"}, {"id": "th_53008", "name": "Stuffed Lamb Tomatoes", "thumb": "https://www.themealdb.com/images/media/meals/u55lbp1585564013.jpg", "category": "Lamb"}], "Irish": [{"id": "th_53036", "name": "Boxty Breakfast", "thumb": "https://www.themealdb.com/images/media/meals/naqyel1608588563.jpg", "category": "Pork"}, {"id": "th_53037", "name": "Coddled pork with cider", "thumb": "https://www.themealdb.com/images/media/meals/7vpsfp1608588991.jpg", "category": "Pork"}, {"id": "th_52998", "name": "Corned Beef and Cabbage", "thumb": "https://www.themealdb.com/images/media/meals/xb97a81583266727.jpg", "category": "Beef"}, {"id": "th_52999", "name": "Crispy Sausages and Greens", "thumb": "https://www.themealdb.com/images/media/meals/st1ifa1583267248.jpg", "category": "Pork"}, {"id": "th_53035", "name": "Ham hock colcannon", "thumb": "https://www.themealdb.com/images/media/meals/n41ny81608588066.jpg", "category": "Pork"}, {"id": "th_52781", "name": "Irish stew", "thumb": "https://www.themealdb.com/images/media/meals/sxxpst1468569714.jpg", "category": "Beef"}, {"id": "th_53038", "name": "Mustard champ", "thumb": "https://www.themealdb.com/images/media/meals/o7p9581608589317.jpg", "category": "Side"}, {"id": "th_53000", "name": "Vegetable Shepherds Pie", "thumb": "https://www.themealdb.com/images/media/meals/w8umt11583268117.jpg", "category": "Beef"}], "Malaysian": [{"id": "th_53049", "name": "Apam balik", "thumb": "https://www.themealdb.com/images/media/meals/adxcbq1619787919.jpg", "category": "Dessert"}, {"id": "th_53050", "name": "Ayam Percik", "thumb": "https://www.themealdb.com/images/media/meals/020z181619788503.jpg", "category": "Chicken"}, {"id": "th_53053", "name": "Beef Rendang", "thumb": "https://www.themealdb.com/images/media/meals/bc8v651619789840.jpg", "category": "Beef"}, {"id": "th_52821", "name": "Laksa King Prawn Noodles", "thumb": "https://www.themealdb.com/images/media/meals/rvypwy1503069308.jpg", "category": "Seafood"}, {"id": "th_53048", "name": "Mee goreng mamak", "thumb": "https://www.themealdb.com/images/media/meals/xquakq1619787532.jpg", "category": "Seafood"}, {"id": "th_53051", "name": "Nasi lemak", "thumb": "https://www.themealdb.com/images/media/meals/wai9bw1619788844.jpg", "category": "Seafood"}, {"id": "th_53052", "name": "Roti john", "thumb": "https://www.themealdb.com/images/media/meals/hx335q1619789561.jpg", "category": "Beef"}, {"id": "th_53054", "name": "Seri muka kuih", "thumb": "https://www.themealdb.com/images/media/meals/6ut2og1619790195.jpg", "category": "Dessert"}], "Portuguese": [{"id": "th_53043", "name": "Fish fofos", "thumb": "https://www.themealdb.com/images/media/meals/a15wsa1614349126.jpg", "category": "Seafood"}, {"id": "th_53041", "name": "Grilled Portuguese sardines", "thumb": "https://www.themealdb.com/images/media/meals/lpd4wy1614347943.jpg", "category": "Seafood"}, {"id": "th_53039", "name": "Piri-piri chicken and slaw", "thumb": "https://www.themealdb.com/images/media/meals/hglsbl1614346998.jpg", "category": "Chicken"}, {"id": "th_53044", "name": "Portuguese barbecued pork (Febras assadas)", "thumb": "https://www.themealdb.com/images/media/meals/cybyue1614349443.jpg", "category": "Pork"}, {"id": "th_53046", "name": "Portuguese custard tarts", "thumb": "https://www.themealdb.com/images/media/meals/vmz7gl1614350221.jpg", "category": "Dessert"}, {"id": "th_53045", "name": "Portuguese fish stew (Caldeirada de peixe)", "thumb": "https://www.themealdb.com/images/media/meals/do7zps1614349775.jpg", "category": "Seafood"}, {"id": "th_53042", "name": "Portuguese prego with green piri-piri", "thumb": "https://www.themealdb.com/images/media/meals/ewcikl1614348364.jpg", "category": "Beef"}, {"id": "th_53040", "name": "Spring onion and prawn empanadas", "thumb": "https://www.themealdb.com/images/media/meals/1c5oso1614347493.jpg", "category": "Seafood"}], "Tunisian": [{"id": "th_52976", "name": "Cashew Ghoriba Biscuits", "thumb": "https://www.themealdb.com/images/media/meals/t3r3ka1560461972.jpg", "category": "Dessert"}, {"id": "th_52969", "name": "Chakchouka ", "thumb": "https://www.themealdb.com/images/media/meals/gpz67p1560458984.jpg", "category": "Miscellaneous"}, {"id": "th_52971", "name": "Kafteji", "thumb": "https://www.themealdb.com/images/media/meals/1bsv1q1560459826.jpg", "category": "Vegetarian"}, {"id": "th_52974", "name": "Keleya Zaara", "thumb": "https://www.themealdb.com/images/media/meals/8x09hy1560460923.jpg", "category": "Lamb"}, {"id": "th_52973", "name": "Leblebi Soup", "thumb": "https://www.themealdb.com/images/media/meals/x2fw9e1560460636.jpg", "category": "Vegetarian"}, {"id": "th_52975", "name": "Tuna and Egg Briks", "thumb": "https://www.themealdb.com/images/media/meals/2dsltq1560461468.jpg", "category": "Seafood"}, {"id": "th_52972", "name": "Tunisian Lamb Soup", "thumb": "https://www.themealdb.com/images/media/meals/t8mn9g1560460231.jpg", "category": "Lamb"}, {"id": "th_52970", "name": "Tunisian Orange Cake", "thumb": "https://www.themealdb.com/images/media/meals/y4jpgq1560459207.jpg", "category": "Dessert"}], "Russian": [{"id": "th_52834", "name": "Beef stroganoff", "thumb": "https://www.themealdb.com/images/media/meals/svprys1511176755.jpg", "category": "Beef"}, {"id": "th_53080", "name": "Blini Pancakes", "thumb": "https://www.themealdb.com/images/media/meals/0206h11699013358.jpg", "category": "Side"}, {"id": "th_53077", "name": "Cabbage Soup (Shchi)", "thumb": "https://www.themealdb.com/images/media/meals/60oc3k1699009846.jpg", "category": "Vegetarian"}, {"id": "th_53079", "name": "Fish Soup (Ukha)", "thumb": "https://www.themealdb.com/images/media/meals/7n8su21699013057.jpg", "category": "Seafood"}, {"id": "th_53083", "name": "Lamb Pilaf (Plov)", "thumb": "https://www.themealdb.com/images/media/meals/kos9av1699014767.jpg", "category": "Lamb"}, {"id": "th_53081", "name": "Potato Salad (Olivier Salad)", "thumb": "https://www.themealdb.com/images/media/meals/ebvuir1699013665.jpg", "category": "Vegetarian"}, {"id": "th_53082", "name": "Strawberries Romanoff", "thumb": "https://www.themealdb.com/images/media/meals/oe8rg51699014028.jpg", "category": "Dessert"}], "Ukrainian": [{"id": "th_53078", "name": "Beetroot Soup (Borscht)", "thumb": "https://www.themealdb.com/images/media/meals/zadvgb1699012544.jpg", "category": "Vegetarian"}, {"id": "th_53313", "name": "Beetroot latkes", "thumb": "https://www.themealdb.com/images/media/meals/qwicc91764368097.jpg", "category": "Vegetarian"}, {"id": "th_53316", "name": "Beetroot pancakes", "thumb": "https://www.themealdb.com/images/media/meals/xlqqhw1764369924.jpg", "category": "Dessert"}, {"id": "th_53311", "name": "Borsch", "thumb": "https://www.themealdb.com/images/media/meals/804v1j1764367088.jpg", "category": "Beef"}, {"id": "th_53315", "name": "Rosemary braised red cabbage with kabanos", "thumb": "https://www.themealdb.com/images/media/meals/s1jxzl1764369317.jpg", "category": "Pork"}, {"id": "th_53314", "name": "Sauerkraut pierogii", "thumb": "https://www.themealdb.com/images/media/meals/gqlxgc1764368767.jpg", "category": "Vegetarian"}, {"id": "th_53312", "name": "Tangy cabbage slaw", "thumb": "https://www.themealdb.com/images/media/meals/e2g2r21764367568.jpg", "category": "Vegetarian"}], "Mexican": [{"id": "th_52826", "name": "Braised Beef Chilli", "thumb": "https://www.themealdb.com/images/media/meals/uuqvwu1504629254.jpg", "category": "Beef"}, {"id": "th_52819", "name": "Cajun spiced fish tacos", "thumb": "https://www.themealdb.com/images/media/meals/uvuyxu1503067369.jpg", "category": "Seafood"}, {"id": "th_52765", "name": "Chicken Enchilada Casserole", "thumb": "https://www.themealdb.com/images/media/meals/qtuwxu1468233098.jpg", "category": "Chicken"}, {"id": "th_52870", "name": "Chickpea Fajitas", "thumb": "https://www.themealdb.com/images/media/meals/tvtxpq1511464705.jpg", "category": "Vegetarian"}, {"id": "th_52830", "name": "Crock Pot Chicken Baked Tacos", "thumb": "https://www.themealdb.com/images/media/meals/ypxvwv1505333929.jpg", "category": "Chicken"}, {"id": "th_53067", "name": "Stuffed Bell Peppers with Quinoa and Black Beans", "thumb": "https://www.themealdb.com/images/media/meals/b66myb1683207208.jpg", "category": "Vegetarian"}], "Moroccan": [{"id": "th_52850", "name": "Chicken Couscous", "thumb": "https://www.themealdb.com/images/media/meals/qxytrx1511304021.jpg", "category": "Chicken"}, {"id": "th_52843", "name": "Lamb Tagine", "thumb": "https://www.themealdb.com/images/media/meals/yuwtuu1511295751.jpg", "category": "Lamb"}, {"id": "th_52782", "name": "Lamb tomato and sweet spices", "thumb": "https://www.themealdb.com/images/media/meals/qtwtss1468572261.jpg", "category": "Lamb"}, {"id": "th_53047", "name": "Moroccan Carrot Soup", "thumb": "https://www.themealdb.com/images/media/meals/jcr46d1614763831.jpg", "category": "Vegetarian"}, {"id": "th_52797", "name": "Spicy North African Potato Salad", "thumb": "https://www.themealdb.com/images/media/meals/urtwux1486983078.jpg", "category": "Vegetarian"}, {"id": "th_52869", "name": "Tahini Lentils", "thumb": "https://www.themealdb.com/images/media/meals/vpxyqt1511464175.jpg", "category": "Vegetarian"}], "Syrian": [{"id": "th_53094", "name": "Baba Ghanoush", "thumb": "https://www.themealdb.com/images/media/meals/dlmh401760524897.jpg", "category": "Side"}, {"id": "th_53091", "name": "Falafel Pita Sandwich with Tahini Sauce", "thumb": "https://www.themealdb.com/images/media/meals/ae6clc1760524712.jpg", "category": "Vegetarian"}, {"id": "th_53092", "name": "Fasoliyyeh Bi Z-Zayt (Syrian Green Beans with Olive Oil)", "thumb": "https://www.themealdb.com/images/media/meals/21yc5s1760524759.jpg", "category": "Vegan"}, {"id": "th_53089", "name": "Syrian Bread", "thumb": "https://www.themealdb.com/images/media/meals/54xzk31760524666.jpg", "category": "Miscellaneous"}, {"id": "th_53095", "name": "Syrian Rice with Meat", "thumb": "https://www.themealdb.com/images/media/meals/zg2b9l1760524940.jpg", "category": "Miscellaneous"}, {"id": "th_53093", "name": "Syrian Spaghetti", "thumb": "https://www.themealdb.com/images/media/meals/5fu4ew1760524857.jpg", "category": "Pasta"}], "Kenyan": [{"id": "th_52967", "name": "Home-made Mandazi", "thumb": "https://www.themealdb.com/images/media/meals/thazgm1555350962.jpg", "category": "Breakfast"}, {"id": "th_53112", "name": "Kenyan Beef Curry", "thumb": "https://www.themealdb.com/images/media/meals/lqampv1762325397.jpg", "category": "Beef"}, {"id": "th_52968", "name": "Mbuzi Choma (Roasted Goat)", "thumb": "https://www.themealdb.com/images/media/meals/cuio7s1555492979.jpg", "category": "Goat"}, {"id": "th_53113", "name": "Sukuma Wiki", "thumb": "https://www.themealdb.com/images/media/meals/60o82j1762341177.jpg", "category": "Vegetarian"}, {"id": "th_53114", "name": "Ugali – Kenyan cornmeal", "thumb": "https://www.themealdb.com/images/media/meals/smoa3h1762341142.jpg", "category": "Breakfast"}], "Slovakia": [{"id": "th_53190", "name": "Bryndzové Halušky", "thumb": "https://www.themealdb.com/images/media/meals/g33c901763365484.jpg", "category": "Pork"}, {"id": "th_53188", "name": "Fašírky", "thumb": "https://www.themealdb.com/images/media/meals/gtpvwp1763363947.jpg", "category": "Pork"}, {"id": "th_53189", "name": "Zemiakové Placky", "thumb": "https://www.themealdb.com/images/media/meals/0umm891763364625.jpg", "category": "Side"}, {"id": "th_53187", "name": "Šúĺlance s Makom", "thumb": "https://www.themealdb.com/images/media/meals/d6o4nu1763362422.jpg", "category": "Dessert"}]}